{
  "last_page": 0,
  "data": [
    {
      "title": "整租·圣骊澳门苑 3室2厅 南/北",
      "community": "圣骊澳门苑",
      "area": "150.00",
      "rooms": "3室2厅",
      "direction": "南/北",
      "floor": "",
      "price": "12075",
      "tags": "",
      "source": "",
      "url": "https://sh.lianjia.com/zufang/SH2014603890942541824.html",
      "rent_type": "整租",
      "location": "普陀-长寿路-圣骊澳门苑",
      "scraped_at": "2026-04-23 15:24:56",
      "region": "changshoulu",
      "unit_price": 80.5,
      "lat": null,
      "lng": null
    },
    {
      "title": "整租·源达大厦 1室1厅 东南",
      "community": "源达大厦",
      "area": "47.59",
      "rooms": "1室1厅",
      "direction": "东南",
      "floor": "",
      "price": "5000",
      "tags": "",
      "source": "",
      "url": "https://sh.lianjia.com/zufang/SH2154796551447248896.html",
      "rent_type": "整租",
      "location": "普陀-长寿路-源达大厦",
      "scraped_at": "2026-04-23 15:24:35",
      "region": "changshoulu",
      "unit_price": 105.1,
      "lat": null,
      "lng": null
    },
    {
      "title": "整租·大上海城市花园 2室2厅 南",
      "community": "大上海城市花园",
      "area": "105.46",
      "rooms": "2室2厅",
      "direction": "南",
      "floor": "",
      "price": "9765",
      "tags": "",
      "source": "",
      "url": "https://sh.lianjia.com/zufang/SH2102764349675274240.html",
      "rent_type": "整租",
      "location": "普陀-长寿路-大上海城市花园",
      "scraped_at": "2026-04-23 15:24:56",
      "region": "changshoulu",
      "unit_price": 92.6,
      "lat": null,
      "lng": null
    },
    {
      "title": "独栋·桂客公寓 静安寺店 亲子房两居室/年租租金8折/民用水电-3052 2室1厅",
      "community": "桂客公寓 静安寺店",
      "area": "45.00",
      "rooms": "2室1厅",
      "direction": "",
      "floor": "",
      "price": "8858",
      "tags": "",
      "source": "",
      "url": "https://sh.lianjia.com/apartment/62347.html",
      "rent_type": "独栋",
      "location": "",
      "scraped_at": "2026-04-23 15:24:39",
      "region": "changshoulu",
      "unit_price": 196.8,
      "lat": null,
      "lng": null
    },
    {
      "title": "整租·乐活居 2室1厅 南",
      "community": "乐活居",
      "area": "68.43",
      "rooms": "2室1厅",
      "direction": "南",
      "floor": "",
      "price": "9200",
      "tags": "",
      "source": "",
      "url": "https://sh.lianjia.com/zufang/SH1889905627103232000.html",
      "rent_type": "整租",
      "location": "普陀-长寿路-乐活居",
      "scraped_at": "2026-04-23 15:24:56",
      "region": "changshoulu",
      "unit_price": 134.4,
      "lat": null,
      "lng": null
    },
    {
      "title": "整租·河滨围城 3室2厅 南/北",
      "community": "河滨围城",
      "area": "129.91",
      "rooms": "3室2厅",
      "direction": "南/北",
      "floor": "",
      "price": "11865",
      "tags": "",
      "source": "",
      "url": "https://sh.lianjia.com/zufang/SH1831923126007496704.html",
      "rent_type": "整租",
      "location": "普陀-长寿路-河滨围城",
      "scraped_at": "2026-04-23 15:24:56",
      "region": "changshoulu",
      "unit_price": 91.3,
      "lat": null,
      "lng": null
    },
    {
      "title": "整租·苏堤春晓名苑 3室2厅 南",
      "community": "苏堤春晓名苑",
      "area": "130.31",
      "rooms": "3室2厅",
      "direction": "南",
      "floor": "",
      "price": "12500",
      "tags": "",
      "source": "",
      "url": "https://sh.lianjia.com/zufang/SH2137802535912603648.html",
      "rent_type": "整租",
      "location": "普陀-长寿路-苏堤春晓名苑",
      "scraped_at": "2026-04-23 15:24:35",
      "region": "changshoulu",
      "unit_price": 95.9,
      "lat": null,
      "lng": null
    },
    {
      "title": "整租·长寿新村(普陀) 2室1厅 南",
      "community": "长寿新村(普陀)",
      "area": "77.23",
      "rooms": "2室1厅",
      "direction": "南",
      "floor": "",
      "price": "7035",
      "tags": "",
      "source": "",
      "url": "https://sh.lianjia.com/zufang/SH2149141160998731776.html",
      "rent_type": "整租",
      "location": "普陀-长寿路-长寿新村(普陀)",
      "scraped_at": "2026-04-23 15:25:00",
      "region": "changshoulu",
      "unit_price": 91.1,
      "lat": null,
      "lng": null
    },
    {
      "title": "独栋·成东公寓 澳门路店 电梯一房 外窗 带厨房 不短租 可以押一付一901-3 1室1厅",
      "community": "成东公寓 澳门路店",
      "area": "20.00",
      "rooms": "1室1厅",
      "direction": "",
      "floor": "",
      "price": "3400",
      "tags": "",
      "source": "",
      "url": "https://sh.lianjia.com/apartment/95131.html",
      "rent_type": "独栋",
      "location": "",
      "scraped_at": "2026-04-23 15:24:35",
      "region": "changshoulu",
      "unit_price": 170.0,
      "lat": null,
      "lng": null
    },
    {
      "title": "整租·云都苑 3室2厅 南",
      "community": "云都苑",
      "area": "124.77",
      "rooms": "3室2厅",
      "direction": "南",
      "floor": "",
      "price": "11025",
      "tags": "",
      "source": "",
      "url": "https://sh.lianjia.com/zufang/SH1934215450950893568.html",
      "rent_type": "整租",
      "location": "普陀-长寿路-云都苑",
      "scraped_at": "2026-04-23 15:24:56",
      "region": "changshoulu",
      "unit_price": 88.4,
      "lat": null,
      "lng": null
    },
    {
      "title": "整租·世纪之门 1室0厅 东北",
      "community": "世纪之门",
      "area": "30.00",
      "rooms": "1室0厅",
      "direction": "东北",
      "floor": "",
      "price": "3885",
      "tags": "",
      "source": "",
      "url": "https://sh.lianjia.com/zufang/SH2014100944140107776.html",
      "rent_type": "整租",
      "location": "普陀-长寿路-世纪之门",
      "scraped_at": "2026-04-23 15:24:56",
      "region": "changshoulu",
      "unit_price": 129.5,
      "lat": null,
      "lng": null
    },
    {
      "title": "整租·昌化路977弄 2室1厅 南",
      "community": "昌化路977弄",
      "area": "52.68",
      "rooms": "2室1厅",
      "direction": "南",
      "floor": "",
      "price": "5800",
      "tags": "",
      "source": "",
      "url": "https://sh.lianjia.com/zufang/SH1899088004106944512.html",
      "rent_type": "整租",
      "location": "普陀-长寿路-昌化路",
      "scraped_at": "2026-04-23 15:24:56",
      "region": "changshoulu",
      "unit_price": 110.1,
      "lat": null,
      "lng": null
    },
    {
      "title": "整租·圣天地服务式公寓 1室0厅 北/东北",
      "community": "圣天地服务式公寓",
      "area": "32.43",
      "rooms": "1室0厅",
      "direction": "北/东北",
      "floor": "",
      "price": "4300",
      "tags": "",
      "source": "",
      "url": "https://sh.lianjia.com/zufang/SH2014604119800545280.html",
      "rent_type": "整租",
      "location": "普陀-长寿路-圣天地服务式公寓",
      "scraped_at": "2026-04-23 15:24:56",
      "region": "changshoulu",
      "unit_price": 132.6,
      "lat": null,
      "lng": null
    },
    {
      "title": "整租·上青佳园 1室1厅 东南",
      "community": "上青佳园",
      "area": "60.00",
      "rooms": "1室1厅",
      "direction": "东南",
      "floor": "",
      "price": "7000",
      "tags": "",
      "source": "",
      "url": "https://sh.lianjia.com/zufang/SH2140650620464398336.html",
      "rent_type": "整租",
      "location": "普陀-长寿路-上青佳园",
      "scraped_at": "2026-04-23 15:24:41",
      "region": "changshoulu",
      "unit_price": 116.7,
      "lat": null,
      "lng": null
    },
    {
      "title": "整租·长寿苑 2室1厅 南",
      "community": "长寿苑",
      "area": "99.13",
      "rooms": "2室1厅",
      "direction": "南",
      "floor": "",
      "price": "10290",
      "tags": "",
      "source": "",
      "url": "https://sh.lianjia.com/zufang/SH2030637366502227968.html",
      "rent_type": "整租",
      "location": "普陀-长寿路-长寿苑",
      "scraped_at": "2026-04-23 15:24:56",
      "region": "changshoulu",
      "unit_price": 103.8,
      "lat": null,
      "lng": null
    },
    {
      "title": "整租·维多利广场 3室2厅 南/北",
      "community": "维多利广场",
      "area": "157.50",
      "rooms": "3室2厅",
      "direction": "南/北",
      "floor": "",
      "price": "17200",
      "tags": "",
      "source": "",
      "url": "https://sh.lianjia.com/zufang/SH2141048698941997056.html",
      "rent_type": "整租",
      "location": "普陀-长寿路-维多利广场",
      "scraped_at": "2026-04-23 15:24:35",
      "region": "changshoulu",
      "unit_price": 109.2,
      "lat": null,
      "lng": null
    },
    {
      "title": "整租·新天大厦 1室1厅 南",
      "community": "新天大厦",
      "area": "32.56",
      "rooms": "1室1厅",
      "direction": "南",
      "floor": "",
      "price": "3500",
      "tags": "",
      "source": "",
      "url": "https://sh.lianjia.com/zufang/SH2014971590302760960.html",
      "rent_type": "整租",
      "location": "普陀-长寿路-新天大厦",
      "scraped_at": "2026-04-23 15:24:56",
      "region": "changshoulu",
      "unit_price": 107.5,
      "lat": null,
      "lng": null
    },
    {
      "title": "独栋·红豆公寓 江宁店 【毕业生押金减半!】普陀区免费网络/民水民电/无中介费. 开间",
      "community": "红豆公寓 江宁店",
      "area": "23.00",
      "rooms": "",
      "direction": "",
      "floor": "",
      "price": "3180-3280",
      "tags": "",
      "source": "",
      "url": "https://sh.lianjia.com/apartment/57173.html",
      "rent_type": "独栋",
      "location": "",
      "scraped_at": "2026-04-23 15:24:39",
      "region": "changshoulu",
      "unit_price": "",
      "lat": null,
      "lng": null
    },
    {
      "title": "整租·大众河滨酒店式公寓 1室1厅 西南",
      "community": "大众河滨酒店式公寓",
      "area": "56.27",
      "rooms": "1室1厅",
      "direction": "西南",
      "floor": "",
      "price": "5100",
      "tags": "",
      "source": "",
      "url": "https://sh.lianjia.com/zufang/SH2157372328948793344.html",
      "rent_type": "整租",
      "location": "普陀-长寿路-大众河滨酒店式公寓",
      "scraped_at": "2026-04-23 15:24:56",
      "region": "changshoulu",
      "unit_price": 90.6,
      "lat": null,
      "lng": null
    },
    {
      "title": "整租·苏堤春晓名苑 2室1厅 南",
      "community": "苏堤春晓名苑",
      "area": "102.77",
      "rooms": "2室1厅",
      "direction": "南",
      "floor": "",
      "price": "12500",
      "tags": "",
      "source": "",
      "url": "https://sh.lianjia.com/zufang/SH2144347844440489984.html",
      "rent_type": "整租",
      "location": "普陀-长寿路-苏堤春晓名苑",
      "scraped_at": "2026-04-23 15:24:41",
      "region": "changshoulu",
      "unit_price": 121.6,
      "lat": null,
      "lng": null
    },
    {
      "title": "整租·华生大厦 2室2厅 南/西南",
      "community": "华生大厦",
      "area": "109.51",
      "rooms": "2室2厅",
      "direction": "南/西南",
      "floor": "",
      "price": "10000",
      "tags": "",
      "source": "",
      "url": "https://sh.lianjia.com/zufang/SH2147676290159738880.html",
      "rent_type": "整租",
      "location": "普陀-长寿路-华生大厦",
      "scraped_at": "2026-04-23 15:24:41",
      "region": "changshoulu",
      "unit_price": 91.3,
      "lat": null,
      "lng": null
    },
    {
      "title": "整租·圣天地服务式公寓 1室1厅 南",
      "community": "圣天地服务式公寓",
      "area": "49.00",
      "rooms": "1室1厅",
      "direction": "南",
      "floor": "",
      "price": "6000",
      "tags": "",
      "source": "",
      "url": "https://sh.lianjia.com/zufang/SH2151955154511855616.html",
      "rent_type": "整租",
      "location": "普陀-长寿路-圣天地服务式公寓",
      "scraped_at": "2026-04-23 15:24:41",
      "region": "changshoulu",
      "unit_price": 122.4,
      "lat": null,
      "lng": null
    },
    {
      "title": "整租·长寿苑 2室2厅 南",
      "community": "长寿苑",
      "area": "92.25",
      "rooms": "2室2厅",
      "direction": "南",
      "floor": "",
      "price": "9800",
      "tags": "",
      "source": "",
      "url": "https://sh.lianjia.com/zufang/SH2152374603324850176.html",
      "rent_type": "整租",
      "location": "普陀-长寿路-长寿苑",
      "scraped_at": "2026-04-23 15:24:35",
      "region": "changshoulu",
      "unit_price": 106.2,
      "lat": null,
      "lng": null
    },
    {
      "title": "整租·正红里 2室0厅 南/北",
      "community": "正红里",
      "area": "43.15",
      "rooms": "2室0厅",
      "direction": "南/北",
      "floor": "",
      "price": "5230",
      "tags": "",
      "source": "",
      "url": "https://sh.lianjia.com/zufang/SH1661398714549272576.html",
      "rent_type": "整租",
      "location": "普陀-长寿路-正红里",
      "scraped_at": "2026-04-23 15:24:53",
      "region": "changshoulu",
      "unit_price": 121.2,
      "lat": null,
      "lng": null
    },
    {
      "title": "整租·澳门公寓 2室2厅 北",
      "community": "澳门公寓",
      "area": "110.27",
      "rooms": "2室2厅",
      "direction": "北",
      "floor": "",
      "price": "9000",
      "tags": "",
      "source": "",
      "url": "https://sh.lianjia.com/zufang/SH2153800599638900736.html",
      "rent_type": "整租",
      "location": "普陀-长寿路-澳门公寓",
      "scraped_at": "2026-04-23 15:24:44",
      "region": "changshoulu",
      "unit_price": 81.6,
      "lat": null,
      "lng": null
    },
    {
      "title": "整租·康怡苑 2室2厅 南/北",
      "community": "康怡苑",
      "area": "95.13",
      "rooms": "2室2厅",
      "direction": "南/北",
      "floor": "",
      "price": "8700",
      "tags": "",
      "source": "",
      "url": "https://sh.lianjia.com/zufang/SH2153466404165124096.html",
      "rent_type": "整租",
      "location": "普陀-长寿路-康怡苑",
      "scraped_at": "2026-04-23 15:24:56",
      "region": "changshoulu",
      "unit_price": 91.5,
      "lat": null,
      "lng": null
    },
    {
      "title": "独栋·莹文公寓 长寿路店 普陀租房看过来！整租一居室 宠物友好随时看房拎包入住 开间",
      "community": "莹文公寓 长寿路店",
      "area": "22.00",
      "rooms": "",
      "direction": "",
      "floor": "",
      "price": "3200-4000",
      "tags": "",
      "source": "",
      "url": "https://sh.lianjia.com/apartment/54364.html",
      "rent_type": "独栋",
      "location": "",
      "scraped_at": "2026-04-23 15:24:41",
      "region": "changshoulu",
      "unit_price": "",
      "lat": null,
      "lng": null
    },
    {
      "title": "整租·长寿路790号 1室0厅 南",
      "community": "长寿路790号",
      "area": "35.53",
      "rooms": "1室0厅",
      "direction": "南",
      "floor": "",
      "price": "4410",
      "tags": "",
      "source": "",
      "url": "https://sh.lianjia.com/zufang/SH2027713800983019520.html",
      "rent_type": "整租",
      "location": "普陀-长寿路-长寿路",
      "scraped_at": "2026-04-23 15:24:56",
      "region": "changshoulu",
      "unit_price": 124.1,
      "lat": null,
      "lng": null
    },
    {
      "title": "整租·正红里 1室1厅 南",
      "community": "正红里",
      "area": "30.24",
      "rooms": "1室1厅",
      "direction": "南",
      "floor": "",
      "price": "4000",
      "tags": "",
      "source": "",
      "url": "https://sh.lianjia.com/zufang/SH2156787675737096192.html",
      "rent_type": "整租",
      "location": "普陀-长寿路-正红里",
      "scraped_at": "2026-04-23 15:24:56",
      "region": "changshoulu",
      "unit_price": 132.3,
      "lat": null,
      "lng": null
    },
    {
      "title": "整租·世纪之门 2室2厅 南/北",
      "community": "世纪之门",
      "area": "125.66",
      "rooms": "2室2厅",
      "direction": "南/北",
      "floor": "",
      "price": "11000",
      "tags": "",
      "source": "",
      "url": "https://sh.lianjia.com/zufang/SH2156056041719070720.html",
      "rent_type": "整租",
      "location": "普陀-长寿路-世纪之门",
      "scraped_at": "2026-04-23 15:24:39",
      "region": "changshoulu",
      "unit_price": 87.5,
      "lat": null,
      "lng": null
    },
    {
      "title": "整租·长寿新村(普陀) 2室1厅 南",
      "community": "长寿新村(普陀)",
      "area": "71.55",
      "rooms": "2室1厅",
      "direction": "南",
      "floor": "",
      "price": "7245",
      "tags": "",
      "source": "",
      "url": "https://sh.lianjia.com/zufang/SH1804076372939767808.html",
      "rent_type": "整租",
      "location": "普陀-长寿路-长寿新村(普陀)",
      "scraped_at": "2026-04-23 15:24:56",
      "region": "changshoulu",
      "unit_price": 101.3,
      "lat": null,
      "lng": null
    },
    {
      "title": "独栋·博克公寓 澳门路店 外窗小复式尊享型 1室1厅",
      "community": "博克公寓 澳门路店 外窗小复式尊享型",
      "area": "26.00",
      "rooms": "1室1厅",
      "direction": "",
      "floor": "",
      "price": "2888",
      "tags": "",
      "source": "",
      "url": "https://sh.lianjia.com/apartment/28856.html",
      "rent_type": "独栋",
      "location": "",
      "scraped_at": "2026-04-23 15:24:41",
      "region": "changshoulu",
      "unit_price": 111.1,
      "lat": null,
      "lng": null
    },
    {
      "title": "整租·音乐广场 2室2厅 南",
      "community": "音乐广场",
      "area": "111.17",
      "rooms": "2室2厅",
      "direction": "南",
      "floor": "",
      "price": "11025",
      "tags": "",
      "source": "",
      "url": "https://sh.lianjia.com/zufang/SH2087129548461178880.html",
      "rent_type": "整租",
      "location": "普陀-长寿路-音乐广场",
      "scraped_at": "2026-04-23 15:24:56",
      "region": "changshoulu",
      "unit_price": 99.2,
      "lat": null,
      "lng": null
    },
    {
      "title": "整租·工商大楼 1室1厅 南",
      "community": "工商大楼",
      "area": "51.58",
      "rooms": "1室1厅",
      "direction": "南",
      "floor": "",
      "price": "6700",
      "tags": "",
      "source": "",
      "url": "https://sh.lianjia.com/zufang/SH2031682482176262144.html",
      "rent_type": "整租",
      "location": "普陀-长寿路-工商大楼",
      "scraped_at": "2026-04-23 15:24:39",
      "region": "changshoulu",
      "unit_price": 129.9,
      "lat": null,
      "lng": null
    },
    {
      "title": "独栋·悦舍公寓 江宁路店 一室阳光房 1室1厅",
      "community": "悦舍公寓 江宁路店 一室阳光房",
      "area": "30.00",
      "rooms": "1室1厅",
      "direction": "",
      "floor": "",
      "price": "6780",
      "tags": "",
      "source": "",
      "url": "https://sh.lianjia.com/apartment/55934.html",
      "rent_type": "独栋",
      "location": "",
      "scraped_at": "2026-04-23 15:24:41",
      "region": "changshoulu",
      "unit_price": 226.0,
      "lat": null,
      "lng": null
    },
    {
      "title": "整租·澳门小区 1室0厅 南",
      "community": "澳门小区",
      "area": "39.54",
      "rooms": "1室0厅",
      "direction": "南",
      "floor": "",
      "price": "4300",
      "tags": "",
      "source": "",
      "url": "https://sh.lianjia.com/zufang/SH2017990292392640512.html",
      "rent_type": "整租",
      "location": "普陀-长寿路-澳门小区",
      "scraped_at": "2026-04-23 15:24:56",
      "region": "changshoulu",
      "unit_price": 108.8,
      "lat": null,
      "lng": null
    },
    {
      "title": "整租·圣天地服务式公寓 1室1厅 东南",
      "community": "圣天地服务式公寓",
      "area": "25.27",
      "rooms": "1室1厅",
      "direction": "东南",
      "floor": "",
      "price": "3990",
      "tags": "",
      "source": "",
      "url": "https://sh.lianjia.com/zufang/SH2017638256719429632.html",
      "rent_type": "整租",
      "location": "普陀-长寿路-圣天地服务式公寓",
      "scraped_at": "2026-04-23 15:24:56",
      "region": "changshoulu",
      "unit_price": 157.9,
      "lat": null,
      "lng": null
    },
    {
      "title": "整租·乐活居 1室1厅 东",
      "community": "乐活居",
      "area": "68.04",
      "rooms": "1室1厅",
      "direction": "东",
      "floor": "",
      "price": "9400",
      "tags": "",
      "source": "",
      "url": "https://sh.lianjia.com/zufang/SH2156063150925938688.html",
      "rent_type": "整租",
      "location": "普陀-长寿路-乐活居",
      "scraped_at": "2026-04-23 15:24:39",
      "region": "changshoulu",
      "unit_price": 138.2,
      "lat": null,
      "lng": null
    },
    {
      "title": "整租·圣天地服务式公寓 1室1厅 东",
      "community": "圣天地服务式公寓",
      "area": "46.00",
      "rooms": "1室1厅",
      "direction": "东",
      "floor": "",
      "price": "5700",
      "tags": "",
      "source": "",
      "url": "https://sh.lianjia.com/zufang/SH1808425202346885120.html",
      "rent_type": "整租",
      "location": "普陀-长寿路-圣天地服务式公寓",
      "scraped_at": "2026-04-23 15:24:53",
      "region": "changshoulu",
      "unit_price": 123.9,
      "lat": null,
      "lng": null
    },
    {
      "title": "整租·浅水湾恺悦名城 4室2厅 南",
      "community": "浅水湾恺悦名城",
      "area": "187.32",
      "rooms": "4室2厅",
      "direction": "南",
      "floor": "",
      "price": "25000",
      "tags": "",
      "source": "",
      "url": "https://sh.lianjia.com/zufang/SH2156288077004275712.html",
      "rent_type": "整租",
      "location": "普陀-长寿路-浅水湾恺悦名城",
      "scraped_at": "2026-04-23 15:24:39",
      "region": "changshoulu",
      "unit_price": 133.5,
      "lat": null,
      "lng": null
    },
    {
      "title": "整租·长寿路555号 1室0厅 南",
      "community": "长寿路555号",
      "area": "29.00",
      "rooms": "1室0厅",
      "direction": "南",
      "floor": "",
      "price": "4050",
      "tags": "",
      "source": "",
      "url": "https://sh.lianjia.com/zufang/SH1952234304276791296.html",
      "rent_type": "整租",
      "location": "普陀-长寿路-长寿路",
      "scraped_at": "2026-04-23 15:24:56",
      "region": "changshoulu",
      "unit_price": 139.7,
      "lat": null,
      "lng": null
    },
    {
      "title": "整租·世纪之门 1室0厅 北",
      "community": "世纪之门",
      "area": "34.91",
      "rooms": "1室0厅",
      "direction": "北",
      "floor": "",
      "price": "4100",
      "tags": "",
      "source": "",
      "url": "https://sh.lianjia.com/zufang/SH1661066322496192512.html",
      "rent_type": "整租",
      "location": "普陀-长寿路-世纪之门",
      "scraped_at": "2026-04-23 15:24:53",
      "region": "changshoulu",
      "unit_price": 117.4,
      "lat": null,
      "lng": null
    },
    {
      "title": "整租·常德名园 2室2厅 南/北",
      "community": "常德名园",
      "area": "105.91",
      "rooms": "2室2厅",
      "direction": "南/北",
      "floor": "",
      "price": "9800",
      "tags": "",
      "source": "",
      "url": "https://sh.lianjia.com/zufang/SH2145113617329029120.html",
      "rent_type": "整租",
      "location": "普陀-长寿路-常德名园",
      "scraped_at": "2026-04-23 15:24:39",
      "region": "changshoulu",
      "unit_price": 92.5,
      "lat": null,
      "lng": null
    },
    {
      "title": "整租·上青佳园 1室1厅 南",
      "community": "上青佳园",
      "area": "60.00",
      "rooms": "1室1厅",
      "direction": "南",
      "floor": "",
      "price": "7800",
      "tags": "",
      "source": "",
      "url": "https://sh.lianjia.com/zufang/SH2148435366133104640.html",
      "rent_type": "整租",
      "location": "普陀-长寿路-上青佳园",
      "scraped_at": "2026-04-23 15:24:41",
      "region": "changshoulu",
      "unit_price": 130.0,
      "lat": null,
      "lng": null
    },
    {
      "title": "整租·澳门公寓 3室1厅 南",
      "community": "澳门公寓",
      "area": "99.07",
      "rooms": "3室1厅",
      "direction": "南",
      "floor": "",
      "price": "9000",
      "tags": "",
      "source": "",
      "url": "https://sh.lianjia.com/zufang/SH2151184900978376704.html",
      "rent_type": "整租",
      "location": "普陀-长寿路-澳门公寓",
      "scraped_at": "2026-04-23 15:24:41",
      "region": "changshoulu",
      "unit_price": 90.8,
      "lat": null,
      "lng": null
    },
    {
      "title": "整租·世纪之门 1室1厅 北",
      "community": "世纪之门",
      "area": "42.06",
      "rooms": "1室1厅",
      "direction": "北",
      "floor": "",
      "price": "4200",
      "tags": "",
      "source": "",
      "url": "https://sh.lianjia.com/zufang/SH1733852452953784320.html",
      "rent_type": "整租",
      "location": "普陀-长寿路-世纪之门",
      "scraped_at": "2026-04-23 15:24:56",
      "region": "changshoulu",
      "unit_price": 99.9,
      "lat": null,
      "lng": null
    },
    {
      "title": "整租·世纪之门 1室0厅 北",
      "community": "世纪之门",
      "area": "29.91",
      "rooms": "1室0厅",
      "direction": "北",
      "floor": "",
      "price": "3800",
      "tags": "",
      "source": "",
      "url": "https://sh.lianjia.com/zufang/SH1895804557657636864.html",
      "rent_type": "整租",
      "location": "普陀-长寿路-世纪之门",
      "scraped_at": "2026-04-23 15:24:56",
      "region": "changshoulu",
      "unit_price": 127.0,
      "lat": null,
      "lng": null
    },
    {
      "title": "整租·圣骊澳门苑 3室2厅 南",
      "community": "圣骊澳门苑",
      "area": "149.27",
      "rooms": "3室2厅",
      "direction": "南",
      "floor": "",
      "price": "13800",
      "tags": "",
      "source": "",
      "url": "https://sh.lianjia.com/zufang/SH2138566502297632768.html",
      "rent_type": "整租",
      "location": "普陀-长寿路-圣骊澳门苑",
      "scraped_at": "2026-04-23 15:24:41",
      "region": "changshoulu",
      "unit_price": 92.4,
      "lat": null,
      "lng": null
    },
    {
      "title": "整租·德怡苑 1室1厅 南",
      "community": "德怡苑",
      "area": "33.79",
      "rooms": "1室1厅",
      "direction": "南",
      "floor": "",
      "price": "5700",
      "tags": "",
      "source": "",
      "url": "https://sh.lianjia.com/zufang/SH2151229989658296320.html",
      "rent_type": "整租",
      "location": "普陀-长寿路-德怡苑",
      "scraped_at": "2026-04-23 15:24:56",
      "region": "changshoulu",
      "unit_price": 168.7,
      "lat": null,
      "lng": null
    },
    {
      "title": "整租·源达大厦 1室1厅 南",
      "community": "源达大厦",
      "area": "35.73",
      "rooms": "1室1厅",
      "direction": "南",
      "floor": "",
      "price": "4830",
      "tags": "",
      "source": "",
      "url": "https://sh.lianjia.com/zufang/SH2070463255532273664.html",
      "rent_type": "整租",
      "location": "普陀-长寿路-源达大厦",
      "scraped_at": "2026-04-23 15:24:56",
      "region": "changshoulu",
      "unit_price": 135.2,
      "lat": null,
      "lng": null
    },
    {
      "title": "独栋·馨乐庭服务公寓 上海馨乐庭长寿路公寓酒店 豪华行政套房 1室1厅",
      "community": "馨乐庭服务公寓 上海馨乐庭长寿路公寓酒店",
      "area": "70.00",
      "rooms": "1室1厅",
      "direction": "",
      "floor": "",
      "price": "19000",
      "tags": "",
      "source": "",
      "url": "https://sh.lianjia.com/apartment/75442.html",
      "rent_type": "独栋",
      "location": "",
      "scraped_at": "2026-04-23 15:24:41",
      "region": "changshoulu",
      "unit_price": 271.4,
      "lat": null,
      "lng": null
    },
    {
      "title": "整租·圣天地服务式公寓 1室1厅 东南",
      "community": "圣天地服务式公寓",
      "area": "34.10",
      "rooms": "1室1厅",
      "direction": "东南",
      "floor": "",
      "price": "4620",
      "tags": "",
      "source": "",
      "url": "https://sh.lianjia.com/zufang/SH2024400437490221056.html",
      "rent_type": "整租",
      "location": "普陀-长寿路-圣天地服务式公寓",
      "scraped_at": "2026-04-23 15:24:56",
      "region": "changshoulu",
      "unit_price": 135.5,
      "lat": null,
      "lng": null
    },
    {
      "title": "整租·圣天地服务式公寓 1室1厅 北",
      "community": "圣天地服务式公寓",
      "area": "32.43",
      "rooms": "1室1厅",
      "direction": "北",
      "floor": "",
      "price": "4400",
      "tags": "",
      "source": "",
      "url": "https://sh.lianjia.com/zufang/SH1850487365810782208.html",
      "rent_type": "整租",
      "location": "普陀-长寿路-圣天地服务式公寓",
      "scraped_at": "2026-04-23 15:24:41",
      "region": "changshoulu",
      "unit_price": 135.7,
      "lat": null,
      "lng": null
    },
    {
      "title": "整租·圣天地服务式公寓 1室1厅 南",
      "community": "圣天地服务式公寓",
      "area": "32.00",
      "rooms": "1室1厅",
      "direction": "南",
      "floor": "",
      "price": "4200",
      "tags": "",
      "source": "",
      "url": "https://sh.lianjia.com/zufang/SH1991453426612961280.html",
      "rent_type": "整租",
      "location": "普陀-长寿路-圣天地服务式公寓",
      "scraped_at": "2026-04-23 15:24:56",
      "region": "changshoulu",
      "unit_price": 131.2,
      "lat": null,
      "lng": null
    },
    {
      "title": "整租·世纪之门 2室2厅 东北",
      "community": "世纪之门",
      "area": "59.36",
      "rooms": "2室2厅",
      "direction": "东北",
      "floor": "",
      "price": "6200",
      "tags": "",
      "source": "",
      "url": "https://sh.lianjia.com/zufang/SH2139985694448156672.html",
      "rent_type": "整租",
      "location": "普陀-长寿路-世纪之门",
      "scraped_at": "2026-04-23 15:24:41",
      "region": "changshoulu",
      "unit_price": 104.4,
      "lat": null,
      "lng": null
    },
    {
      "title": "整租·大众河滨大厦 2室1厅 南",
      "community": "大众河滨大厦",
      "area": "97.48",
      "rooms": "2室1厅",
      "direction": "南",
      "floor": "",
      "price": "11000",
      "tags": "",
      "source": "",
      "url": "https://sh.lianjia.com/zufang/SH2147539450421313536.html",
      "rent_type": "整租",
      "location": "普陀-长寿路-大众河滨大厦",
      "scraped_at": "2026-04-23 15:24:41",
      "region": "changshoulu",
      "unit_price": 112.8,
      "lat": null,
      "lng": null
    },
    {
      "title": "整租·世纪之门 1室0厅 东",
      "community": "世纪之门",
      "area": "29.91",
      "rooms": "1室0厅",
      "direction": "东",
      "floor": "",
      "price": "3850",
      "tags": "",
      "source": "",
      "url": "https://sh.lianjia.com/zufang/SH2149359911404830720.html",
      "rent_type": "整租",
      "location": "普陀-长寿路-世纪之门",
      "scraped_at": "2026-04-23 15:24:41",
      "region": "changshoulu",
      "unit_price": 128.7,
      "lat": null,
      "lng": null
    },
    {
      "title": "整租·圣天地服务式公寓 1室1厅 南",
      "community": "圣天地服务式公寓",
      "area": "45.00",
      "rooms": "1室1厅",
      "direction": "南",
      "floor": "",
      "price": "4500",
      "tags": "",
      "source": "",
      "url": "https://sh.lianjia.com/zufang/SH2077979096817598464.html",
      "rent_type": "整租",
      "location": "普陀-长寿路-圣天地服务式公寓",
      "scraped_at": "2026-04-23 15:24:41",
      "region": "changshoulu",
      "unit_price": 100.0,
      "lat": null,
      "lng": null
    },
    {
      "title": "整租·汇丽花园 1室1厅 南",
      "community": "汇丽花园",
      "area": "58.81",
      "rooms": "1室1厅",
      "direction": "南",
      "floor": "",
      "price": "7500",
      "tags": "",
      "source": "",
      "url": "https://sh.lianjia.com/zufang/SH2154545434767392768.html",
      "rent_type": "整租",
      "location": "普陀-长寿路-汇丽花园",
      "scraped_at": "2026-04-23 15:24:44",
      "region": "changshoulu",
      "unit_price": 127.5,
      "lat": null,
      "lng": null
    },
    {
      "title": "整租·十里都华 1室1厅 南",
      "community": "十里都华",
      "area": "68.54",
      "rooms": "1室1厅",
      "direction": "南",
      "floor": "",
      "price": "8800",
      "tags": "",
      "source": "",
      "url": "https://sh.lianjia.com/zufang/SH2155197323427184640.html",
      "rent_type": "整租",
      "location": "普陀-长寿路-十里都华",
      "scraped_at": "2026-04-23 15:24:44",
      "region": "changshoulu",
      "unit_price": 128.4,
      "lat": null,
      "lng": null
    },
    {
      "title": "整租·长寿路790号 1室1厅 东/南",
      "community": "长寿路790号",
      "area": "38.85",
      "rooms": "1室1厅",
      "direction": "东/南",
      "floor": "",
      "price": "4350",
      "tags": "",
      "source": "",
      "url": "https://sh.lianjia.com/zufang/SH2154114299612626944.html",
      "rent_type": "整租",
      "location": "普陀-长寿路-长寿路",
      "scraped_at": "2026-04-23 15:24:44",
      "region": "changshoulu",
      "unit_price": 112.0,
      "lat": null,
      "lng": null
    },
    {
      "title": "整租·华生大厦 2室2厅 西南",
      "community": "华生大厦",
      "area": "109.51",
      "rooms": "2室2厅",
      "direction": "西南",
      "floor": "",
      "price": "10000",
      "tags": "",
      "source": "",
      "url": "https://sh.lianjia.com/zufang/SH2141213450087432192.html",
      "rent_type": "整租",
      "location": "普陀-长寿路-华生大厦",
      "scraped_at": "2026-04-23 15:24:44",
      "region": "changshoulu",
      "unit_price": 91.3,
      "lat": null,
      "lng": null
    },
    {
      "title": "整租·常德大厦 2室2厅 西南/西",
      "community": "常德大厦",
      "area": "119.26",
      "rooms": "2室2厅",
      "direction": "西南/西",
      "floor": "",
      "price": "10800",
      "tags": "",
      "source": "",
      "url": "https://sh.lianjia.com/zufang/SH2154230084569923584.html",
      "rent_type": "整租",
      "location": "普陀-长寿路-常德大厦",
      "scraped_at": "2026-04-23 15:24:44",
      "region": "changshoulu",
      "unit_price": 90.6,
      "lat": null,
      "lng": null
    },
    {
      "title": "整租·大上海城市花园 3室2厅 南",
      "community": "大上海城市花园",
      "area": "122.90",
      "rooms": "3室2厅",
      "direction": "南",
      "floor": "",
      "price": "12500",
      "tags": "",
      "source": "",
      "url": "https://sh.lianjia.com/zufang/SH2138480720752934912.html",
      "rent_type": "整租",
      "location": "普陀-长寿路-大上海城市花园",
      "scraped_at": "2026-04-23 15:24:44",
      "region": "changshoulu",
      "unit_price": 101.7,
      "lat": null,
      "lng": null
    },
    {
      "title": "整租·上青佳园 3室2厅 南",
      "community": "上青佳园",
      "area": "153.84",
      "rooms": "3室2厅",
      "direction": "南",
      "floor": "",
      "price": "15500",
      "tags": "",
      "source": "",
      "url": "https://sh.lianjia.com/zufang/SH2123733382100680704.html",
      "rent_type": "整租",
      "location": "普陀-长寿路-上青佳园",
      "scraped_at": "2026-04-23 15:24:44",
      "region": "changshoulu",
      "unit_price": 100.8,
      "lat": null,
      "lng": null
    },
    {
      "title": "整租·乐怡苑(普陀) 2室1厅 南",
      "community": "乐怡苑(普陀)",
      "area": "69.25",
      "rooms": "2室1厅",
      "direction": "南",
      "floor": "",
      "price": "7800",
      "tags": "",
      "source": "",
      "url": "https://sh.lianjia.com/zufang/SH2152323289760923648.html",
      "rent_type": "整租",
      "location": "普陀-长寿路-乐怡苑(普陀)",
      "scraped_at": "2026-04-23 15:24:44",
      "region": "changshoulu",
      "unit_price": 112.6,
      "lat": null,
      "lng": null
    },
    {
      "title": "整租·世纪之门 1室1厅 北",
      "community": "世纪之门",
      "area": "59.36",
      "rooms": "1室1厅",
      "direction": "北",
      "floor": "",
      "price": "6500",
      "tags": "",
      "source": "",
      "url": "https://sh.lianjia.com/zufang/SH2139734490476445696.html",
      "rent_type": "整租",
      "location": "普陀-长寿路-世纪之门",
      "scraped_at": "2026-04-23 15:24:44",
      "region": "changshoulu",
      "unit_price": 109.5,
      "lat": null,
      "lng": null
    },
    {
      "title": "整租·大众河滨酒店式公寓 1室1厅 南",
      "community": "大众河滨酒店式公寓",
      "area": "48.47",
      "rooms": "1室1厅",
      "direction": "南",
      "floor": "",
      "price": "5600",
      "tags": "",
      "source": "",
      "url": "https://sh.lianjia.com/zufang/SH2154545326797619200.html",
      "rent_type": "整租",
      "location": "普陀-长寿路-大众河滨酒店式公寓",
      "scraped_at": "2026-04-23 15:24:44",
      "region": "changshoulu",
      "unit_price": 115.5,
      "lat": null,
      "lng": null
    },
    {
      "title": "整租·圣骊澳门苑 1室1厅 南",
      "community": "圣骊澳门苑",
      "area": "87.28",
      "rooms": "1室1厅",
      "direction": "南",
      "floor": "",
      "price": "9600",
      "tags": "",
      "source": "",
      "url": "https://sh.lianjia.com/zufang/SH2126907995819343872.html",
      "rent_type": "整租",
      "location": "普陀-长寿路-圣骊澳门苑",
      "scraped_at": "2026-04-23 15:24:44",
      "region": "changshoulu",
      "unit_price": 110.0,
      "lat": null,
      "lng": null
    },
    {
      "title": "整租·玉佛城 3室2厅 东/东南/北",
      "community": "玉佛城",
      "area": "139.03",
      "rooms": "3室2厅",
      "direction": "东/东南/北",
      "floor": "",
      "price": "18000",
      "tags": "",
      "source": "",
      "url": "https://sh.lianjia.com/zufang/SH2122623138339487744.html",
      "rent_type": "整租",
      "location": "普陀-长寿路-玉佛城",
      "scraped_at": "2026-04-23 15:24:44",
      "region": "changshoulu",
      "unit_price": 129.5,
      "lat": null,
      "lng": null
    },
    {
      "title": "整租·世纪之门 1室1厅 南",
      "community": "世纪之门",
      "area": "57.79",
      "rooms": "1室1厅",
      "direction": "南",
      "floor": "",
      "price": "6500",
      "tags": "",
      "source": "",
      "url": "https://sh.lianjia.com/zufang/SH2142938177298497536.html",
      "rent_type": "整租",
      "location": "普陀-长寿路-世纪之门",
      "scraped_at": "2026-04-23 15:24:44",
      "region": "changshoulu",
      "unit_price": 112.5,
      "lat": null,
      "lng": null
    },
    {
      "title": "整租·汇丽花园 1室1厅 南",
      "community": "汇丽花园",
      "area": "59.36",
      "rooms": "1室1厅",
      "direction": "南",
      "floor": "",
      "price": "7500",
      "tags": "",
      "source": "",
      "url": "https://sh.lianjia.com/zufang/SH2131728077187710976.html",
      "rent_type": "整租",
      "location": "普陀-长寿路-汇丽花园",
      "scraped_at": "2026-04-23 15:24:44",
      "region": "changshoulu",
      "unit_price": 126.3,
      "lat": null,
      "lng": null
    },
    {
      "title": "整租·世纪商务大厦 1室1厅 东",
      "community": "世纪商务大厦",
      "area": "47.82",
      "rooms": "1室1厅",
      "direction": "东",
      "floor": "",
      "price": "7900",
      "tags": "",
      "source": "",
      "url": "https://sh.lianjia.com/zufang/SH2155704298837639168.html",
      "rent_type": "整租",
      "location": "普陀-长寿路-世纪商务大厦",
      "scraped_at": "2026-04-23 15:24:44",
      "region": "changshoulu",
      "unit_price": 165.2,
      "lat": null,
      "lng": null
    },
    {
      "title": "整租·乐活居 2室2厅 西南",
      "community": "乐活居",
      "area": "76.89",
      "rooms": "2室2厅",
      "direction": "西南",
      "floor": "",
      "price": "13000",
      "tags": "",
      "source": "",
      "url": "https://sh.lianjia.com/zufang/SH2144298001718312960.html",
      "rent_type": "整租",
      "location": "普陀-长寿路-乐活居",
      "scraped_at": "2026-04-23 15:24:44",
      "region": "changshoulu",
      "unit_price": 169.1,
      "lat": null,
      "lng": null
    },
    {
      "title": "整租·泰极大厦 2室1厅 南",
      "community": "泰极大厦",
      "area": "111.49",
      "rooms": "2室1厅",
      "direction": "南",
      "floor": "",
      "price": "15000",
      "tags": "",
      "source": "",
      "url": "https://sh.lianjia.com/zufang/SH2126671236023975936.html",
      "rent_type": "整租",
      "location": "普陀-长寿路-泰极大厦",
      "scraped_at": "2026-04-23 15:24:44",
      "region": "changshoulu",
      "unit_price": 134.5,
      "lat": null,
      "lng": null
    },
    {
      "title": "整租·澳门小区 1室0厅 南",
      "community": "澳门小区",
      "area": "35.92",
      "rooms": "1室0厅",
      "direction": "南",
      "floor": "",
      "price": "4600",
      "tags": "",
      "source": "",
      "url": "https://sh.lianjia.com/zufang/SH2144827605293989888.html",
      "rent_type": "整租",
      "location": "普陀-长寿路-澳门小区",
      "scraped_at": "2026-04-23 15:24:44",
      "region": "changshoulu",
      "unit_price": 128.1,
      "lat": null,
      "lng": null
    },
    {
      "title": "整租·锦绣里 3室2厅 南/北",
      "community": "锦绣里",
      "area": "220.56",
      "rooms": "3室2厅",
      "direction": "南/北",
      "floor": "",
      "price": "35000",
      "tags": "",
      "source": "",
      "url": "https://sh.lianjia.com/zufang/SH2144022391519444992.html",
      "rent_type": "整租",
      "location": "普陀-长寿路-锦绣里",
      "scraped_at": "2026-04-23 15:24:44",
      "region": "changshoulu",
      "unit_price": 158.7,
      "lat": null,
      "lng": null
    },
    {
      "title": "整租·新天大厦 1室1厅 东南",
      "community": "新天大厦",
      "area": "28.80",
      "rooms": "1室1厅",
      "direction": "东南",
      "floor": "",
      "price": "3600",
      "tags": "",
      "source": "",
      "url": "https://sh.lianjia.com/zufang/SH2145420925640638464.html",
      "rent_type": "整租",
      "location": "普陀-长寿路-新天大厦",
      "scraped_at": "2026-04-23 15:24:44",
      "region": "changshoulu",
      "unit_price": 125.0,
      "lat": null,
      "lng": null
    },
    {
      "title": "整租·澳门大厦 2室2厅 东北",
      "community": "澳门大厦",
      "area": "130.68",
      "rooms": "2室2厅",
      "direction": "东北",
      "floor": "",
      "price": "11000",
      "tags": "",
      "source": "",
      "url": "https://sh.lianjia.com/zufang/SH2138097221231443968.html",
      "rent_type": "整租",
      "location": "普陀-长寿路-澳门大厦",
      "scraped_at": "2026-04-23 15:24:44",
      "region": "changshoulu",
      "unit_price": 84.2,
      "lat": null,
      "lng": null
    },
    {
      "title": "整租·乐活居 2室2厅 东",
      "community": "乐活居",
      "area": "83.00",
      "rooms": "2室2厅",
      "direction": "东",
      "floor": "",
      "price": "14500",
      "tags": "",
      "source": "",
      "url": "https://sh.lianjia.com/zufang/SH2145542629209669632.html",
      "rent_type": "整租",
      "location": "普陀-长寿路-乐活居",
      "scraped_at": "2026-04-23 15:24:44",
      "region": "changshoulu",
      "unit_price": 174.7,
      "lat": null,
      "lng": null
    },
    {
      "title": "整租·世纪之门 2室1厅 东",
      "community": "世纪之门",
      "area": "59.82",
      "rooms": "2室1厅",
      "direction": "东",
      "floor": "",
      "price": "6500",
      "tags": "",
      "source": "",
      "url": "https://sh.lianjia.com/zufang/SH2149417302263595008.html",
      "rent_type": "整租",
      "location": "普陀-长寿路-世纪之门",
      "scraped_at": "2026-04-23 15:24:44",
      "region": "changshoulu",
      "unit_price": 108.7,
      "lat": null,
      "lng": null
    },
    {
      "title": "整租·德怡苑 2室1厅 东南",
      "community": "德怡苑",
      "area": "49.80",
      "rooms": "2室1厅",
      "direction": "东南",
      "floor": "",
      "price": "6800",
      "tags": "",
      "source": "",
      "url": "https://sh.lianjia.com/zufang/SH2145917628403679232.html",
      "rent_type": "整租",
      "location": "普陀-长寿路-德怡苑",
      "scraped_at": "2026-04-23 15:24:44",
      "region": "changshoulu",
      "unit_price": 136.5,
      "lat": null,
      "lng": null
    },
    {
      "title": "整租·秋水云庐 3室2厅 南/西南",
      "community": "秋水云庐",
      "area": "137.94",
      "rooms": "3室2厅",
      "direction": "南/西南",
      "floor": "",
      "price": "14800",
      "tags": "",
      "source": "",
      "url": "https://sh.lianjia.com/zufang/SH2144702251837423616.html",
      "rent_type": "整租",
      "location": "普陀-长寿路-秋水云庐",
      "scraped_at": "2026-04-23 15:24:44",
      "region": "changshoulu",
      "unit_price": 107.3,
      "lat": null,
      "lng": null
    },
    {
      "title": "整租·长寿大厦 2室2厅 西南",
      "community": "长寿大厦",
      "area": "134.18",
      "rooms": "2室2厅",
      "direction": "西南",
      "floor": "",
      "price": "18500",
      "tags": "",
      "source": "",
      "url": "https://sh.lianjia.com/zufang/SH2138202794014801920.html",
      "rent_type": "整租",
      "location": "普陀-长寿路-长寿大厦",
      "scraped_at": "2026-04-23 15:24:44",
      "region": "changshoulu",
      "unit_price": 137.9,
      "lat": null,
      "lng": null
    },
    {
      "title": "整租·苏堤春晓名苑 2室1厅 南",
      "community": "苏堤春晓名苑",
      "area": "114.33",
      "rooms": "2室1厅",
      "direction": "南",
      "floor": "",
      "price": "11000",
      "tags": "",
      "source": "",
      "url": "https://sh.lianjia.com/zufang/SH2143043186736496640.html",
      "rent_type": "整租",
      "location": "普陀-长寿路-苏堤春晓名苑",
      "scraped_at": "2026-04-23 15:24:44",
      "region": "changshoulu",
      "unit_price": 96.2,
      "lat": null,
      "lng": null
    },
    {
      "title": "整租·绿洲城市花园 2室1厅 南/北",
      "community": "绿洲城市花园",
      "area": "91.00",
      "rooms": "2室1厅",
      "direction": "南/北",
      "floor": "",
      "price": "11000",
      "tags": "",
      "source": "",
      "url": "https://sh.lianjia.com/zufang/SH2146986004014170112.html",
      "rent_type": "整租",
      "location": "普陀-长寿路-绿洲城市花园",
      "scraped_at": "2026-04-23 15:24:44",
      "region": "changshoulu",
      "unit_price": 120.9,
      "lat": null,
      "lng": null
    },
    {
      "title": "整租·光明城市 3室2厅 南",
      "community": "光明城市",
      "area": "154.04",
      "rooms": "3室2厅",
      "direction": "南",
      "floor": "",
      "price": "18500",
      "tags": "",
      "source": "",
      "url": "https://sh.lianjia.com/zufang/SH2126629580599984128.html",
      "rent_type": "整租",
      "location": "普陀-长寿路-光明城市",
      "scraped_at": "2026-04-23 15:24:44",
      "region": "changshoulu",
      "unit_price": 120.1,
      "lat": null,
      "lng": null
    },
    {
      "title": "整租·长寿新村(普陀) 1室1厅 南",
      "community": "长寿新村(普陀)",
      "area": "46.09",
      "rooms": "1室1厅",
      "direction": "南",
      "floor": "",
      "price": "5500",
      "tags": "",
      "source": "",
      "url": "https://sh.lianjia.com/zufang/SH2151907856465526784.html",
      "rent_type": "整租",
      "location": "普陀-长寿路-长寿新村(普陀)",
      "scraped_at": "2026-04-23 15:24:47",
      "region": "changshoulu",
      "unit_price": 119.3,
      "lat": null,
      "lng": null
    },
    {
      "title": "整租·星海大厦 2室1厅 南",
      "community": "星海大厦",
      "area": "110.24",
      "rooms": "2室1厅",
      "direction": "南",
      "floor": "",
      "price": "9800",
      "tags": "",
      "source": "",
      "url": "https://sh.lianjia.com/zufang/SH2099139591259815936.html",
      "rent_type": "整租",
      "location": "普陀-长寿路-星海大厦",
      "scraped_at": "2026-04-23 15:24:47",
      "region": "changshoulu",
      "unit_price": 88.9,
      "lat": null,
      "lng": null
    },
    {
      "title": "整租·九茂小区 1室1厅 南",
      "community": "九茂小区",
      "area": "60.00",
      "rooms": "1室1厅",
      "direction": "南",
      "floor": "",
      "price": "5900",
      "tags": "",
      "source": "",
      "url": "https://sh.lianjia.com/zufang/SH2153806974066622464.html",
      "rent_type": "整租",
      "location": "普陀-长寿路-九茂小区",
      "scraped_at": "2026-04-23 15:24:47",
      "region": "changshoulu",
      "unit_price": 98.3,
      "lat": null,
      "lng": null
    },
    {
      "title": "整租·世纪之门 1室1厅 南",
      "community": "世纪之门",
      "area": "60.61",
      "rooms": "1室1厅",
      "direction": "南",
      "floor": "",
      "price": "7000",
      "tags": "",
      "source": "",
      "url": "https://sh.lianjia.com/zufang/SH2139699177733488640.html",
      "rent_type": "整租",
      "location": "普陀-长寿路-世纪之门",
      "scraped_at": "2026-04-23 15:24:47",
      "region": "changshoulu",
      "unit_price": 115.5,
      "lat": null,
      "lng": null
    },
    {
      "title": "整租·光明城市 3室2厅 南",
      "community": "光明城市",
      "area": "148.11",
      "rooms": "3室2厅",
      "direction": "南",
      "floor": "",
      "price": "22000",
      "tags": "",
      "source": "",
      "url": "https://sh.lianjia.com/zufang/SH2110230740393263104.html",
      "rent_type": "整租",
      "location": "普陀-长寿路-光明城市",
      "scraped_at": "2026-04-23 15:24:47",
      "region": "changshoulu",
      "unit_price": 148.5,
      "lat": null,
      "lng": null
    },
    {
      "title": "整租·苏堤春晓名苑 3室2厅 南/北",
      "community": "苏堤春晓名苑",
      "area": "118.87",
      "rooms": "3室2厅",
      "direction": "南/北",
      "floor": "",
      "price": "15500",
      "tags": "",
      "source": "",
      "url": "https://sh.lianjia.com/zufang/SH2018325352983560192.html",
      "rent_type": "整租",
      "location": "普陀-长寿路-苏堤春晓名苑",
      "scraped_at": "2026-04-23 15:24:47",
      "region": "changshoulu",
      "unit_price": 130.4,
      "lat": null,
      "lng": null
    },
    {
      "title": "整租·澳门小区 1室0厅 北",
      "community": "澳门小区",
      "area": "28.80",
      "rooms": "1室0厅",
      "direction": "北",
      "floor": "",
      "price": "4000",
      "tags": "",
      "source": "",
      "url": "https://sh.lianjia.com/zufang/SH2150822652204285952.html",
      "rent_type": "整租",
      "location": "普陀-长寿路-澳门小区",
      "scraped_at": "2026-04-23 15:24:47",
      "region": "changshoulu",
      "unit_price": 138.9,
      "lat": null,
      "lng": null
    },
    {
      "title": "整租·德怡苑 2室0厅 西南",
      "community": "德怡苑",
      "area": "70.43",
      "rooms": "2室0厅",
      "direction": "西南",
      "floor": "",
      "price": "7188",
      "tags": "",
      "source": "",
      "url": "https://sh.lianjia.com/zufang/SH2138701079322296320.html",
      "rent_type": "整租",
      "location": "普陀-长寿路-德怡苑",
      "scraped_at": "2026-04-23 15:24:47",
      "region": "changshoulu",
      "unit_price": 102.1,
      "lat": null,
      "lng": null
    },
    {
      "title": "整租·长寿路790号 1室1厅 南",
      "community": "长寿路790号",
      "area": "29.90",
      "rooms": "1室1厅",
      "direction": "南",
      "floor": "",
      "price": "4500",
      "tags": "",
      "source": "",
      "url": "https://sh.lianjia.com/zufang/SH2145490927496462336.html",
      "rent_type": "整租",
      "location": "普陀-长寿路-长寿路",
      "scraped_at": "2026-04-23 15:24:47",
      "region": "changshoulu",
      "unit_price": 150.5,
      "lat": null,
      "lng": null
    },
    {
      "title": "整租·汇丽花园 1室1厅 南",
      "community": "汇丽花园",
      "area": "59.91",
      "rooms": "1室1厅",
      "direction": "南",
      "floor": "",
      "price": "7200",
      "tags": "",
      "source": "",
      "url": "https://sh.lianjia.com/zufang/SH2153435999252774912.html",
      "rent_type": "整租",
      "location": "普陀-长寿路-汇丽花园",
      "scraped_at": "2026-04-23 15:24:47",
      "region": "changshoulu",
      "unit_price": 120.2,
      "lat": null,
      "lng": null
    },
    {
      "title": "整租·绿洲城市花园 2室1厅 南/北",
      "community": "绿洲城市花园",
      "area": "70.46",
      "rooms": "2室1厅",
      "direction": "南/北",
      "floor": "",
      "price": "9500",
      "tags": "",
      "source": "",
      "url": "https://sh.lianjia.com/zufang/SH2138596609531838464.html",
      "rent_type": "整租",
      "location": "普陀-长寿路-绿洲城市花园",
      "scraped_at": "2026-04-23 15:24:47",
      "region": "changshoulu",
      "unit_price": 134.8,
      "lat": null,
      "lng": null
    },
    {
      "title": "整租·圣天地服务式公寓 1室1厅 南",
      "community": "圣天地服务式公寓",
      "area": "35.10",
      "rooms": "1室1厅",
      "direction": "南",
      "floor": "",
      "price": "5000",
      "tags": "",
      "source": "",
      "url": "https://sh.lianjia.com/zufang/SH2153777645551091712.html",
      "rent_type": "整租",
      "location": "普陀-长寿路-圣天地服务式公寓",
      "scraped_at": "2026-04-23 15:24:47",
      "region": "changshoulu",
      "unit_price": 142.5,
      "lat": null,
      "lng": null
    },
    {
      "title": "整租·圣天地服务式公寓 1室1厅 北",
      "community": "圣天地服务式公寓",
      "area": "25.00",
      "rooms": "1室1厅",
      "direction": "北",
      "floor": "",
      "price": "4000",
      "tags": "",
      "source": "",
      "url": "https://sh.lianjia.com/zufang/SH2124078782347214848.html",
      "rent_type": "整租",
      "location": "普陀-长寿路-圣天地服务式公寓",
      "scraped_at": "2026-04-23 15:24:47",
      "region": "changshoulu",
      "unit_price": 160.0,
      "lat": null,
      "lng": null
    },
    {
      "title": "整租·世纪之门 1室1厅 南",
      "community": "世纪之门",
      "area": "54.86",
      "rooms": "1室1厅",
      "direction": "南",
      "floor": "",
      "price": "6300",
      "tags": "",
      "source": "",
      "url": "https://sh.lianjia.com/zufang/SH2137512775767818240.html",
      "rent_type": "整租",
      "location": "普陀-长寿路-世纪之门",
      "scraped_at": "2026-04-23 15:24:47",
      "region": "changshoulu",
      "unit_price": 114.8,
      "lat": null,
      "lng": null
    },
    {
      "title": "整租·世纪之门 2室2厅 南",
      "community": "世纪之门",
      "area": "91.62",
      "rooms": "2室2厅",
      "direction": "南",
      "floor": "",
      "price": "12000",
      "tags": "",
      "source": "",
      "url": "https://sh.lianjia.com/zufang/SH2145434373346820096.html",
      "rent_type": "整租",
      "location": "普陀-长寿路-世纪之门",
      "scraped_at": "2026-04-23 15:24:47",
      "region": "changshoulu",
      "unit_price": 131.0,
      "lat": null,
      "lng": null
    },
    {
      "title": "整租·大众河滨酒店式公寓 1室0厅 西",
      "community": "大众河滨酒店式公寓",
      "area": "40.00",
      "rooms": "1室0厅",
      "direction": "西",
      "floor": "",
      "price": "4800",
      "tags": "",
      "source": "",
      "url": "https://sh.lianjia.com/zufang/SH2143322178261614592.html",
      "rent_type": "整租",
      "location": "普陀-长寿路-大众河滨酒店式公寓",
      "scraped_at": "2026-04-23 15:24:47",
      "region": "changshoulu",
      "unit_price": 120.0,
      "lat": null,
      "lng": null
    },
    {
      "title": "整租·圣天地服务式公寓 1室1厅 东",
      "community": "圣天地服务式公寓",
      "area": "25.27",
      "rooms": "1室1厅",
      "direction": "东",
      "floor": "",
      "price": "3980",
      "tags": "",
      "source": "",
      "url": "https://sh.lianjia.com/zufang/SH2148646587549614080.html",
      "rent_type": "整租",
      "location": "普陀-长寿路-圣天地服务式公寓",
      "scraped_at": "2026-04-23 15:24:47",
      "region": "changshoulu",
      "unit_price": 157.5,
      "lat": null,
      "lng": null
    },
    {
      "title": "整租·华侨城 2室2厅 南",
      "community": "华侨城",
      "area": "89.97",
      "rooms": "2室2厅",
      "direction": "南",
      "floor": "",
      "price": "16000",
      "tags": "",
      "source": "",
      "url": "https://sh.lianjia.com/zufang/SH2148429098618191872.html",
      "rent_type": "整租",
      "location": "普陀-长寿路-华侨城",
      "scraped_at": "2026-04-23 15:24:47",
      "region": "changshoulu",
      "unit_price": 177.8,
      "lat": null,
      "lng": null
    },
    {
      "title": "整租·世纪之门 1室1厅 西北",
      "community": "世纪之门",
      "area": "30.20",
      "rooms": "1室1厅",
      "direction": "西北",
      "floor": "",
      "price": "3300",
      "tags": "",
      "source": "",
      "url": "https://sh.lianjia.com/zufang/SH2153068576116834304.html",
      "rent_type": "整租",
      "location": "普陀-长寿路-世纪之门",
      "scraped_at": "2026-04-23 15:24:47",
      "region": "changshoulu",
      "unit_price": 109.3,
      "lat": null,
      "lng": null
    },
    {
      "title": "整租·圣天地商务楼 2室1厅 南",
      "community": "圣天地商务楼",
      "area": "114.00",
      "rooms": "2室1厅",
      "direction": "南",
      "floor": "",
      "price": "9000",
      "tags": "",
      "source": "",
      "url": "https://sh.lianjia.com/zufang/SH2136402946894594048.html",
      "rent_type": "整租",
      "location": "普陀-长寿路-圣天地商务楼",
      "scraped_at": "2026-04-23 15:24:47",
      "region": "changshoulu",
      "unit_price": 78.9,
      "lat": null,
      "lng": null
    },
    {
      "title": "整租·澳门小区 1室1厅 南",
      "community": "澳门小区",
      "area": "35.92",
      "rooms": "1室1厅",
      "direction": "南",
      "floor": "",
      "price": "4800",
      "tags": "",
      "source": "",
      "url": "https://sh.lianjia.com/zufang/SH2128412054573285376.html",
      "rent_type": "整租",
      "location": "普陀-长寿路-澳门小区",
      "scraped_at": "2026-04-23 15:24:47",
      "region": "changshoulu",
      "unit_price": 133.6,
      "lat": null,
      "lng": null
    },
    {
      "title": "整租·苏堤春晓名苑 2室2厅 南",
      "community": "苏堤春晓名苑",
      "area": "107.00",
      "rooms": "2室2厅",
      "direction": "南",
      "floor": "",
      "price": "12000",
      "tags": "",
      "source": "",
      "url": "https://sh.lianjia.com/zufang/SH2143702685109452800.html",
      "rent_type": "整租",
      "location": "普陀-长寿路-苏堤春晓名苑",
      "scraped_at": "2026-04-23 15:24:47",
      "region": "changshoulu",
      "unit_price": 112.1,
      "lat": null,
      "lng": null
    },
    {
      "title": "整租·世纪之门 1室1厅 东北",
      "community": "世纪之门",
      "area": "28.99",
      "rooms": "1室1厅",
      "direction": "东北",
      "floor": "",
      "price": "4500",
      "tags": "",
      "source": "",
      "url": "https://sh.lianjia.com/zufang/SH2156038015233818624.html",
      "rent_type": "整租",
      "location": "普陀-长寿路-世纪之门",
      "scraped_at": "2026-04-23 15:24:47",
      "region": "changshoulu",
      "unit_price": 155.2,
      "lat": null,
      "lng": null
    },
    {
      "title": "整租·工商大楼 1室1厅 南",
      "community": "工商大楼",
      "area": "51.41",
      "rooms": "1室1厅",
      "direction": "南",
      "floor": "",
      "price": "6600",
      "tags": "",
      "source": "",
      "url": "https://sh.lianjia.com/zufang/SH2143615515384348672.html",
      "rent_type": "整租",
      "location": "普陀-长寿路-工商大楼",
      "scraped_at": "2026-04-23 15:24:47",
      "region": "changshoulu",
      "unit_price": 128.4,
      "lat": null,
      "lng": null
    },
    {
      "title": "整租·新天大厦 1室1厅 南",
      "community": "新天大厦",
      "area": "61.93",
      "rooms": "1室1厅",
      "direction": "南",
      "floor": "",
      "price": "5500",
      "tags": "",
      "source": "",
      "url": "https://sh.lianjia.com/zufang/SH2003024796446621696.html",
      "rent_type": "整租",
      "location": "普陀-长寿路-新天大厦",
      "scraped_at": "2026-04-23 15:24:47",
      "region": "changshoulu",
      "unit_price": 88.8,
      "lat": null,
      "lng": null
    },
    {
      "title": "整租·世纪之门 1室1厅 北",
      "community": "世纪之门",
      "area": "29.91",
      "rooms": "1室1厅",
      "direction": "北",
      "floor": "",
      "price": "3900",
      "tags": "",
      "source": "",
      "url": "https://sh.lianjia.com/zufang/SH2097310134651846656.html",
      "rent_type": "整租",
      "location": "普陀-长寿路-世纪之门",
      "scraped_at": "2026-04-23 15:24:47",
      "region": "changshoulu",
      "unit_price": 130.4,
      "lat": null,
      "lng": null
    },
    {
      "title": "整租·浅水湾恺悦名城 3室2厅 南/北",
      "community": "浅水湾恺悦名城",
      "area": "140.96",
      "rooms": "3室2厅",
      "direction": "南/北",
      "floor": "",
      "price": "23800",
      "tags": "",
      "source": "",
      "url": "https://sh.lianjia.com/zufang/SH2138563117049708544.html",
      "rent_type": "整租",
      "location": "普陀-长寿路-浅水湾恺悦名城",
      "scraped_at": "2026-04-23 15:24:47",
      "region": "changshoulu",
      "unit_price": 168.8,
      "lat": null,
      "lng": null
    },
    {
      "title": "整租·常澳馨苑 2室1厅 南",
      "community": "常澳馨苑",
      "area": "51.60",
      "rooms": "2室1厅",
      "direction": "南",
      "floor": "",
      "price": "5500",
      "tags": "",
      "source": "",
      "url": "https://sh.lianjia.com/zufang/SH2150850732977291264.html",
      "rent_type": "整租",
      "location": "普陀-长寿路-常澳馨苑",
      "scraped_at": "2026-04-23 15:24:47",
      "region": "changshoulu",
      "unit_price": 106.6,
      "lat": null,
      "lng": null
    },
    {
      "title": "整租·工商大楼 2室1厅 西北",
      "community": "工商大楼",
      "area": "68.63",
      "rooms": "2室1厅",
      "direction": "西北",
      "floor": "",
      "price": "6600",
      "tags": "",
      "source": "",
      "url": "https://sh.lianjia.com/zufang/SH2143211294340153344.html",
      "rent_type": "整租",
      "location": "普陀-长寿路-工商大楼",
      "scraped_at": "2026-04-23 15:24:51",
      "region": "changshoulu",
      "unit_price": 96.2,
      "lat": null,
      "lng": null
    },
    {
      "title": "整租·锦绣里 3室2厅 南",
      "community": "锦绣里",
      "area": "164.00",
      "rooms": "3室2厅",
      "direction": "南",
      "floor": "",
      "price": "36000",
      "tags": "",
      "source": "",
      "url": "https://sh.lianjia.com/zufang/SH2051175439191244800.html",
      "rent_type": "整租",
      "location": "普陀-长寿路-锦绣里",
      "scraped_at": "2026-04-23 15:24:51",
      "region": "changshoulu",
      "unit_price": 219.5,
      "lat": null,
      "lng": null
    },
    {
      "title": "整租·莘远大厦 3室2厅 东/西",
      "community": "莘远大厦",
      "area": "135.83",
      "rooms": "3室2厅",
      "direction": "东/西",
      "floor": "",
      "price": "10000",
      "tags": "",
      "source": "",
      "url": "https://sh.lianjia.com/zufang/SH2156397580462850048.html",
      "rent_type": "整租",
      "location": "普陀-长寿路-莘远大厦",
      "scraped_at": "2026-04-23 15:24:51",
      "region": "changshoulu",
      "unit_price": 73.6,
      "lat": null,
      "lng": null
    },
    {
      "title": "整租·世纪之门 1室1厅 北",
      "community": "世纪之门",
      "area": "29.91",
      "rooms": "1室1厅",
      "direction": "北",
      "floor": "",
      "price": "4300",
      "tags": "",
      "source": "",
      "url": "https://sh.lianjia.com/zufang/SH2108542064760193024.html",
      "rent_type": "整租",
      "location": "普陀-长寿路-世纪之门",
      "scraped_at": "2026-04-23 15:24:51",
      "region": "changshoulu",
      "unit_price": 143.8,
      "lat": null,
      "lng": null
    },
    {
      "title": "整租·阳光新苑 2室2厅 南",
      "community": "阳光新苑",
      "area": "124.48",
      "rooms": "2室2厅",
      "direction": "南",
      "floor": "",
      "price": "10800",
      "tags": "",
      "source": "",
      "url": "https://sh.lianjia.com/zufang/SH2007020708206477312.html",
      "rent_type": "整租",
      "location": "普陀-长寿路-阳光新苑",
      "scraped_at": "2026-04-23 15:24:51",
      "region": "changshoulu",
      "unit_price": 86.8,
      "lat": null,
      "lng": null
    },
    {
      "title": "整租·苏堤春晓名苑 4室2厅 南",
      "community": "苏堤春晓名苑",
      "area": "188.47",
      "rooms": "4室2厅",
      "direction": "南",
      "floor": "",
      "price": "38000",
      "tags": "",
      "source": "",
      "url": "https://sh.lianjia.com/zufang/SH2138138037056438272.html",
      "rent_type": "整租",
      "location": "普陀-长寿路-苏堤春晓名苑",
      "scraped_at": "2026-04-23 15:24:51",
      "region": "changshoulu",
      "unit_price": 201.6,
      "lat": null,
      "lng": null
    },
    {
      "title": "整租·银座花苑 4室2厅 西南",
      "community": "银座花苑",
      "area": "177.00",
      "rooms": "4室2厅",
      "direction": "西南",
      "floor": "",
      "price": "15800",
      "tags": "",
      "source": "",
      "url": "https://sh.lianjia.com/zufang/SH2090720134078398464.html",
      "rent_type": "整租",
      "location": "普陀-长寿路-银座花苑",
      "scraped_at": "2026-04-23 15:24:51",
      "region": "changshoulu",
      "unit_price": 89.3,
      "lat": null,
      "lng": null
    },
    {
      "title": "整租·世纪之门 1室1厅 南",
      "community": "世纪之门",
      "area": "68.91",
      "rooms": "1室1厅",
      "direction": "南",
      "floor": "",
      "price": "6500",
      "tags": "",
      "source": "",
      "url": "https://sh.lianjia.com/zufang/SH2154801731332997120.html",
      "rent_type": "整租",
      "location": "普陀-长寿路-世纪之门",
      "scraped_at": "2026-04-23 15:24:51",
      "region": "changshoulu",
      "unit_price": 94.3,
      "lat": null,
      "lng": null
    },
    {
      "title": "整租·长寿路505弄 2室1厅 南",
      "community": "长寿路505弄",
      "area": "58.71",
      "rooms": "2室1厅",
      "direction": "南",
      "floor": "",
      "price": "6500",
      "tags": "",
      "source": "",
      "url": "https://sh.lianjia.com/zufang/SH2148392161777811456.html",
      "rent_type": "整租",
      "location": "普陀-长寿路-长寿路",
      "scraped_at": "2026-04-23 15:24:51",
      "region": "changshoulu",
      "unit_price": 110.7,
      "lat": null,
      "lng": null
    },
    {
      "title": "整租·华侨城 2室1厅 南",
      "community": "华侨城",
      "area": "86.41",
      "rooms": "2室1厅",
      "direction": "南",
      "floor": "",
      "price": "16500",
      "tags": "",
      "source": "",
      "url": "https://sh.lianjia.com/zufang/SH2150216240579215360.html",
      "rent_type": "整租",
      "location": "普陀-长寿路-华侨城",
      "scraped_at": "2026-04-23 15:24:51",
      "region": "changshoulu",
      "unit_price": 191.0,
      "lat": null,
      "lng": null
    },
    {
      "title": "整租·圣天地服务式公寓 1室1厅 南",
      "community": "圣天地服务式公寓",
      "area": "32.43",
      "rooms": "1室1厅",
      "direction": "南",
      "floor": "",
      "price": "5000",
      "tags": "",
      "source": "",
      "url": "https://sh.lianjia.com/zufang/SH2151326503386742784.html",
      "rent_type": "整租",
      "location": "普陀-长寿路-圣天地服务式公寓",
      "scraped_at": "2026-04-23 15:24:51",
      "region": "changshoulu",
      "unit_price": 154.2,
      "lat": null,
      "lng": null
    },
    {
      "title": "整租·世纪之门 2室2厅 复式 南",
      "community": "世纪之门",
      "area": "127.42",
      "rooms": "2室2厅",
      "direction": "",
      "floor": "",
      "price": "9900",
      "tags": "",
      "source": "",
      "url": "https://sh.lianjia.com/zufang/SH2152267871005179904.html",
      "rent_type": "整租",
      "location": "普陀-长寿路-世纪之门",
      "scraped_at": "2026-04-23 15:24:51",
      "region": "changshoulu",
      "unit_price": 77.7,
      "lat": null,
      "lng": null
    },
    {
      "title": "整租·河滨围城 3室2厅 南/北",
      "community": "河滨围城",
      "area": "132.31",
      "rooms": "3室2厅",
      "direction": "南/北",
      "floor": "",
      "price": "15000",
      "tags": "",
      "source": "",
      "url": "https://sh.lianjia.com/zufang/SH1957845024792117248.html",
      "rent_type": "整租",
      "location": "普陀-长寿路-河滨围城",
      "scraped_at": "2026-04-23 15:24:51",
      "region": "changshoulu",
      "unit_price": 113.4,
      "lat": null,
      "lng": null
    },
    {
      "title": "整租·绿洲城市花园 3室2厅 南",
      "community": "绿洲城市花园",
      "area": "120.67",
      "rooms": "3室2厅",
      "direction": "南",
      "floor": "",
      "price": "11800",
      "tags": "",
      "source": "",
      "url": "https://sh.lianjia.com/zufang/SH2157132665101221888.html",
      "rent_type": "整租",
      "location": "普陀-长寿路-绿洲城市花园",
      "scraped_at": "2026-04-23 15:24:51",
      "region": "changshoulu",
      "unit_price": 97.8,
      "lat": null,
      "lng": null
    },
    {
      "title": "整租·常德大厦 4室2厅 南",
      "community": "常德大厦",
      "area": "183.05",
      "rooms": "4室2厅",
      "direction": "南",
      "floor": "",
      "price": "19000",
      "tags": "",
      "source": "",
      "url": "https://sh.lianjia.com/zufang/SH1979119711681511424.html",
      "rent_type": "整租",
      "location": "普陀-长寿路-常德大厦",
      "scraped_at": "2026-04-23 15:24:51",
      "region": "changshoulu",
      "unit_price": 103.8,
      "lat": null,
      "lng": null
    },
    {
      "title": "整租·上青佳园 1室1厅 西南",
      "community": "上青佳园",
      "area": "64.56",
      "rooms": "1室1厅",
      "direction": "西南",
      "floor": "",
      "price": "9000",
      "tags": "",
      "source": "",
      "url": "https://sh.lianjia.com/zufang/SH2087489297488805888.html",
      "rent_type": "整租",
      "location": "普陀-长寿路-上青佳园",
      "scraped_at": "2026-04-23 15:24:51",
      "region": "changshoulu",
      "unit_price": 139.4,
      "lat": null,
      "lng": null
    },
    {
      "title": "整租·世纪之门 2室1厅 南",
      "community": "世纪之门",
      "area": "60.61",
      "rooms": "2室1厅",
      "direction": "南",
      "floor": "",
      "price": "6000",
      "tags": "",
      "source": "",
      "url": "https://sh.lianjia.com/zufang/SH2007435139214213120.html",
      "rent_type": "整租",
      "location": "普陀-长寿路-世纪之门",
      "scraped_at": "2026-04-23 15:24:51",
      "region": "changshoulu",
      "unit_price": 99.0,
      "lat": null,
      "lng": null
    },
    {
      "title": "整租·富丽大厦 1室2厅 南",
      "community": "富丽大厦",
      "area": "114.22",
      "rooms": "1室2厅",
      "direction": "南",
      "floor": "",
      "price": "10000",
      "tags": "",
      "source": "",
      "url": "https://sh.lianjia.com/zufang/SH2150243133563076608.html",
      "rent_type": "整租",
      "location": "普陀-长寿路-富丽大厦",
      "scraped_at": "2026-04-23 15:24:51",
      "region": "changshoulu",
      "unit_price": 87.6,
      "lat": null,
      "lng": null
    },
    {
      "title": "整租·长寿苑 4室2厅 南/北",
      "community": "长寿苑",
      "area": "173.78",
      "rooms": "4室2厅",
      "direction": "南/北",
      "floor": "",
      "price": "18000",
      "tags": "",
      "source": "",
      "url": "https://sh.lianjia.com/zufang/SH2152657626809237504.html",
      "rent_type": "整租",
      "location": "普陀-长寿路-长寿苑",
      "scraped_at": "2026-04-23 15:24:51",
      "region": "changshoulu",
      "unit_price": 103.6,
      "lat": null,
      "lng": null
    },
    {
      "title": "整租·昆仑商务中心 2室0厅 西北",
      "community": "昆仑商务中心",
      "area": "93.00",
      "rooms": "2室0厅",
      "direction": "西北",
      "floor": "",
      "price": "7450",
      "tags": "",
      "source": "",
      "url": "https://sh.lianjia.com/zufang/SH2109183941205295104.html",
      "rent_type": "整租",
      "location": "普陀-长寿路-昆仑商务中心",
      "scraped_at": "2026-04-23 15:24:51",
      "region": "changshoulu",
      "unit_price": 80.1,
      "lat": null,
      "lng": null
    },
    {
      "title": "整租·澳门小区 1室0厅 北",
      "community": "澳门小区",
      "area": "31.37",
      "rooms": "1室0厅",
      "direction": "北",
      "floor": "",
      "price": "3900",
      "tags": "",
      "source": "",
      "url": "https://sh.lianjia.com/zufang/SH2065353830693863424.html",
      "rent_type": "整租",
      "location": "普陀-长寿路-澳门小区",
      "scraped_at": "2026-04-23 15:24:51",
      "region": "changshoulu",
      "unit_price": 124.3,
      "lat": null,
      "lng": null
    },
    {
      "title": "整租·水岸茗苑 0室0厅 南",
      "community": "水岸茗苑",
      "area": "30.00",
      "rooms": "0室0厅",
      "direction": "南",
      "floor": "",
      "price": "1500",
      "tags": "",
      "source": "",
      "url": "https://sh.lianjia.com/zufang/SH2155957275292860416.html",
      "rent_type": "整租",
      "location": "普陀-长寿路-水岸茗苑",
      "scraped_at": "2026-04-23 15:24:51",
      "region": "changshoulu",
      "unit_price": 50.0,
      "lat": null,
      "lng": null
    },
    {
      "title": "整租·苏堤春晓名苑 1室0厅 南",
      "community": "苏堤春晓名苑",
      "area": "30.00",
      "rooms": "1室0厅",
      "direction": "南",
      "floor": "",
      "price": "1500",
      "tags": "",
      "source": "",
      "url": "https://sh.lianjia.com/zufang/SH2151289535986663424.html",
      "rent_type": "整租",
      "location": "普陀-长寿路-苏堤春晓名苑",
      "scraped_at": "2026-04-23 15:24:51",
      "region": "changshoulu",
      "unit_price": 50.0,
      "lat": null,
      "lng": null
    },
    {
      "title": "整租·长寿路535号 1室0厅 南",
      "community": "长寿路535号",
      "area": "14.00",
      "rooms": "1室0厅",
      "direction": "南",
      "floor": "",
      "price": "4000",
      "tags": "",
      "source": "",
      "url": "https://sh.lianjia.com/zufang/SH2147235288328437760.html",
      "rent_type": "整租",
      "location": "普陀-长寿路-长寿路",
      "scraped_at": "2026-04-23 15:24:51",
      "region": "changshoulu",
      "unit_price": 285.7,
      "lat": null,
      "lng": null
    },
    {
      "title": "整租·悦达国际大厦 3室1厅 南",
      "community": "悦达国际大厦",
      "area": "123.08",
      "rooms": "3室1厅",
      "direction": "南",
      "floor": "",
      "price": "11000",
      "tags": "",
      "source": "",
      "url": "https://sh.lianjia.com/zufang/SH2153426669942079488.html",
      "rent_type": "整租",
      "location": "普陀-长寿路-悦达国际大厦",
      "scraped_at": "2026-04-23 15:24:51",
      "region": "changshoulu",
      "unit_price": 89.4,
      "lat": null,
      "lng": null
    },
    {
      "title": "整租·美豪怡致酒店 1室1厅 南",
      "community": "美豪怡致酒店",
      "area": "43.00",
      "rooms": "1室1厅",
      "direction": "南",
      "floor": "",
      "price": "6200",
      "tags": "",
      "source": "",
      "url": "https://sh.lianjia.com/zufang/SH2154154989365231616.html",
      "rent_type": "整租",
      "location": "普陀-长寿路-美豪怡致酒店",
      "scraped_at": "2026-04-23 15:24:51",
      "region": "changshoulu",
      "unit_price": 144.2,
      "lat": null,
      "lng": null
    },
    {
      "title": "整租·世纪之门 2室2厅 南/北",
      "community": "世纪之门",
      "area": "101.82",
      "rooms": "2室2厅",
      "direction": "南/北",
      "floor": "",
      "price": "9500",
      "tags": "",
      "source": "",
      "url": "https://sh.lianjia.com/zufang/SH2156349800683929600.html",
      "rent_type": "整租",
      "location": "普陀-长寿路-世纪之门",
      "scraped_at": "2026-04-23 15:24:51",
      "region": "changshoulu",
      "unit_price": 93.3,
      "lat": null,
      "lng": null
    },
    {
      "title": "整租·圣天地服务式公寓 1室0厅 东",
      "community": "圣天地服务式公寓",
      "area": "34.40",
      "rooms": "1室0厅",
      "direction": "东",
      "floor": "",
      "price": "5000",
      "tags": "",
      "source": "",
      "url": "https://sh.lianjia.com/zufang/SH2156412460427378688.html",
      "rent_type": "整租",
      "location": "普陀-长寿路-圣天地服务式公寓",
      "scraped_at": "2026-04-23 15:24:51",
      "region": "changshoulu",
      "unit_price": 145.3,
      "lat": null,
      "lng": null
    },
    {
      "title": "整租·日月星辰 4室2厅 南",
      "community": "日月星辰",
      "area": "200.00",
      "rooms": "4室2厅",
      "direction": "南",
      "floor": "",
      "price": "21000",
      "tags": "",
      "source": "",
      "url": "https://sh.lianjia.com/zufang/SH2142829749414658048.html",
      "rent_type": "整租",
      "location": "普陀-长寿路-日月星辰",
      "scraped_at": "2026-04-23 15:24:51",
      "region": "changshoulu",
      "unit_price": 105.0,
      "lat": null,
      "lng": null
    },
    {
      "title": "整租·澳门小区 1室1厅 南",
      "community": "澳门小区",
      "area": "31.00",
      "rooms": "1室1厅",
      "direction": "南",
      "floor": "",
      "price": "4500",
      "tags": "",
      "source": "",
      "url": "https://sh.lianjia.com/zufang/SH2147647677825810432.html",
      "rent_type": "整租",
      "location": "普陀-长寿路-澳门小区",
      "scraped_at": "2026-04-23 15:24:51",
      "region": "changshoulu",
      "unit_price": 145.2,
      "lat": null,
      "lng": null
    },
    {
      "title": "整租·乐活居 2室1厅 西",
      "community": "乐活居",
      "area": "76.89",
      "rooms": "2室1厅",
      "direction": "西",
      "floor": "",
      "price": "13500",
      "tags": "",
      "source": "",
      "url": "https://sh.lianjia.com/zufang/SH2153047736495112192.html",
      "rent_type": "整租",
      "location": "普陀-长寿路-乐活居",
      "scraped_at": "2026-04-23 15:24:53",
      "region": "changshoulu",
      "unit_price": 175.6,
      "lat": null,
      "lng": null
    },
    {
      "title": "整租·上青佳园 2室1厅 南/北",
      "community": "上青佳园",
      "area": "78.40",
      "rooms": "2室1厅",
      "direction": "南/北",
      "floor": "",
      "price": "11500",
      "tags": "",
      "source": "",
      "url": "https://sh.lianjia.com/zufang/SH2130537380308844544.html",
      "rent_type": "整租",
      "location": "普陀-长寿路-上青佳园",
      "scraped_at": "2026-04-23 15:24:53",
      "region": "changshoulu",
      "unit_price": 146.7,
      "lat": null,
      "lng": null
    },
    {
      "title": "整租·长寿新村(普陀) 2室1厅 南",
      "community": "长寿新村(普陀)",
      "area": "77.23",
      "rooms": "2室1厅",
      "direction": "南",
      "floor": "",
      "price": "6980",
      "tags": "",
      "source": "",
      "url": "https://sh.lianjia.com/zufang/SH2156340051640844288.html",
      "rent_type": "整租",
      "location": "普陀-长寿路-长寿新村(普陀)",
      "scraped_at": "2026-04-23 15:24:53",
      "region": "changshoulu",
      "unit_price": 90.4,
      "lat": null,
      "lng": null
    },
    {
      "title": "整租·大上海城市花园 2室2厅 南",
      "community": "大上海城市花园",
      "area": "93.00",
      "rooms": "2室2厅",
      "direction": "南",
      "floor": "",
      "price": "11500",
      "tags": "",
      "source": "",
      "url": "https://sh.lianjia.com/zufang/SH2153884246987505664.html",
      "rent_type": "整租",
      "location": "普陀-长寿路-大上海城市花园",
      "scraped_at": "2026-04-23 15:24:53",
      "region": "changshoulu",
      "unit_price": 123.7,
      "lat": null,
      "lng": null
    },
    {
      "title": "整租·水岸茗苑 2室2厅 南",
      "community": "水岸茗苑",
      "area": "111.37",
      "rooms": "2室2厅",
      "direction": "南",
      "floor": "",
      "price": "13000",
      "tags": "",
      "source": "",
      "url": "https://sh.lianjia.com/zufang/SH2147349451461623808.html",
      "rent_type": "整租",
      "location": "普陀-长寿路-水岸茗苑",
      "scraped_at": "2026-04-23 15:24:53",
      "region": "changshoulu",
      "unit_price": 116.7,
      "lat": null,
      "lng": null
    },
    {
      "title": "整租·上海知音苑 2室2厅 南/北",
      "community": "上海知音苑",
      "area": "110.00",
      "rooms": "2室2厅",
      "direction": "南/北",
      "floor": "",
      "price": "9500",
      "tags": "",
      "source": "",
      "url": "https://sh.lianjia.com/zufang/SH2121556614333857792.html",
      "rent_type": "整租",
      "location": "普陀-长寿路-上海知音苑",
      "scraped_at": "2026-04-23 15:24:53",
      "region": "changshoulu",
      "unit_price": 86.4,
      "lat": null,
      "lng": null
    },
    {
      "title": "整租·圣骊澳门苑 2室2厅 南",
      "community": "圣骊澳门苑",
      "area": "148.64",
      "rooms": "2室2厅",
      "direction": "南",
      "floor": "",
      "price": "22000",
      "tags": "",
      "source": "",
      "url": "https://sh.lianjia.com/zufang/SH2094694332169715712.html",
      "rent_type": "整租",
      "location": "普陀-长寿路-圣骊澳门苑",
      "scraped_at": "2026-04-23 15:24:53",
      "region": "changshoulu",
      "unit_price": 148.0,
      "lat": null,
      "lng": null
    },
    {
      "title": "整租·澳门大厦 2室2厅 东南",
      "community": "澳门大厦",
      "area": "87.18",
      "rooms": "2室2厅",
      "direction": "东南",
      "floor": "",
      "price": "8200",
      "tags": "",
      "source": "",
      "url": "https://sh.lianjia.com/zufang/SH2104055152787849216.html",
      "rent_type": "整租",
      "location": "普陀-长寿路-澳门大厦",
      "scraped_at": "2026-04-23 15:24:53",
      "region": "changshoulu",
      "unit_price": 94.1,
      "lat": null,
      "lng": null
    },
    {
      "title": "整租·富丽花苑 1室2厅 南",
      "community": "富丽花苑",
      "area": "70.05",
      "rooms": "1室2厅",
      "direction": "南",
      "floor": "",
      "price": "7600",
      "tags": "",
      "source": "",
      "url": "https://sh.lianjia.com/zufang/SH2155533290252009472.html",
      "rent_type": "整租",
      "location": "普陀-长寿路-富丽花苑",
      "scraped_at": "2026-04-23 15:24:53",
      "region": "changshoulu",
      "unit_price": 108.5,
      "lat": null,
      "lng": null
    },
    {
      "title": "整租·世纪之门 1室1厅 北",
      "community": "世纪之门",
      "area": "34.91",
      "rooms": "1室1厅",
      "direction": "北",
      "floor": "",
      "price": "4300",
      "tags": "",
      "source": "",
      "url": "https://sh.lianjia.com/zufang/SH2157800297588588544.html",
      "rent_type": "整租",
      "location": "普陀-长寿路-世纪之门",
      "scraped_at": "2026-04-23 15:24:53",
      "region": "changshoulu",
      "unit_price": 123.2,
      "lat": null,
      "lng": null
    },
    {
      "title": "整租·源达大厦 1室1厅 南",
      "community": "源达大厦",
      "area": "38.30",
      "rooms": "1室1厅",
      "direction": "南",
      "floor": "",
      "price": "5600",
      "tags": "",
      "source": "",
      "url": "https://sh.lianjia.com/zufang/SH2146191032721604608.html",
      "rent_type": "整租",
      "location": "普陀-长寿路-源达大厦",
      "scraped_at": "2026-04-23 15:24:53",
      "region": "changshoulu",
      "unit_price": 146.2,
      "lat": null,
      "lng": null
    },
    {
      "title": "整租·世纪商务大厦 1室1厅 南",
      "community": "世纪商务大厦",
      "area": "47.82",
      "rooms": "1室1厅",
      "direction": "南",
      "floor": "",
      "price": "8500",
      "tags": "",
      "source": "",
      "url": "https://sh.lianjia.com/zufang/SH2158427765689286656.html",
      "rent_type": "整租",
      "location": "普陀-长寿路-世纪商务大厦",
      "scraped_at": "2026-04-23 15:24:53",
      "region": "changshoulu",
      "unit_price": 177.7,
      "lat": null,
      "lng": null
    },
    {
      "title": "整租·大众河滨酒店式公寓 1室1厅 南",
      "community": "大众河滨酒店式公寓",
      "area": "47.00",
      "rooms": "1室1厅",
      "direction": "南",
      "floor": "",
      "price": "5200",
      "tags": "",
      "source": "",
      "url": "https://sh.lianjia.com/zufang/SH2157049059276226560.html",
      "rent_type": "整租",
      "location": "普陀-长寿路-大众河滨酒店式公寓",
      "scraped_at": "2026-04-23 15:24:53",
      "region": "changshoulu",
      "unit_price": 110.6,
      "lat": null,
      "lng": null
    },
    {
      "title": "整租·华侨城 3室2厅 南",
      "community": "华侨城",
      "area": "166.87",
      "rooms": "3室2厅",
      "direction": "南",
      "floor": "",
      "price": "25000",
      "tags": "",
      "source": "",
      "url": "https://sh.lianjia.com/zufang/SH2157126043557691392.html",
      "rent_type": "整租",
      "location": "普陀-长寿路-华侨城",
      "scraped_at": "2026-04-23 15:24:53",
      "region": "changshoulu",
      "unit_price": 149.8,
      "lat": null,
      "lng": null
    },
    {
      "title": "整租·世纪之门 1室0厅 东北",
      "community": "世纪之门",
      "area": "29.91",
      "rooms": "1室0厅",
      "direction": "东北",
      "floor": "",
      "price": "3650",
      "tags": "",
      "source": "",
      "url": "https://sh.lianjia.com/zufang/SH2122598868423016448.html",
      "rent_type": "整租",
      "location": "普陀-长寿路-世纪之门",
      "scraped_at": "2026-04-23 15:24:53",
      "region": "changshoulu",
      "unit_price": 122.0,
      "lat": null,
      "lng": null
    },
    {
      "title": "整租·乐怡苑(普陀) 1室1厅 南",
      "community": "乐怡苑(普陀)",
      "area": "40.42",
      "rooms": "1室1厅",
      "direction": "南",
      "floor": "",
      "price": "5300",
      "tags": "",
      "source": "",
      "url": "https://sh.lianjia.com/zufang/SH2148085609015541760.html",
      "rent_type": "整租",
      "location": "普陀-长寿路-乐怡苑(普陀)",
      "scraped_at": "2026-04-23 15:24:53",
      "region": "changshoulu",
      "unit_price": 131.1,
      "lat": null,
      "lng": null
    },
    {
      "title": "整租·上青佳园 2室1厅 南",
      "community": "上青佳园",
      "area": "64.56",
      "rooms": "2室1厅",
      "direction": "南",
      "floor": "",
      "price": "8600",
      "tags": "",
      "source": "",
      "url": "https://sh.lianjia.com/zufang/SH2137420021733785600.html",
      "rent_type": "整租",
      "location": "普陀-长寿路-上青佳园",
      "scraped_at": "2026-04-23 15:24:53",
      "region": "changshoulu",
      "unit_price": 133.2,
      "lat": null,
      "lng": null
    },
    {
      "title": "整租·大上海城市花园 2室2厅 南",
      "community": "大上海城市花园",
      "area": "98.23",
      "rooms": "2室2厅",
      "direction": "南",
      "floor": "",
      "price": "12500",
      "tags": "",
      "source": "",
      "url": "https://sh.lianjia.com/zufang/SH2141754558555095040.html",
      "rent_type": "整租",
      "location": "普陀-长寿路-大上海城市花园",
      "scraped_at": "2026-04-23 15:24:53",
      "region": "changshoulu",
      "unit_price": 127.3,
      "lat": null,
      "lng": null
    },
    {
      "title": "整租·世纪之门 1室1厅 北",
      "community": "世纪之门",
      "area": "42.06",
      "rooms": "1室1厅",
      "direction": "北",
      "floor": "",
      "price": "4800",
      "tags": "",
      "source": "",
      "url": "https://sh.lianjia.com/zufang/SH2157022977764360192.html",
      "rent_type": "整租",
      "location": "普陀-长寿路-世纪之门",
      "scraped_at": "2026-04-23 15:24:53",
      "region": "changshoulu",
      "unit_price": 114.1,
      "lat": null,
      "lng": null
    },
    {
      "title": "整租·上海知音苑 2室2厅 南/北",
      "community": "上海知音苑",
      "area": "112.90",
      "rooms": "2室2厅",
      "direction": "南/北",
      "floor": "",
      "price": "12000",
      "tags": "",
      "source": "",
      "url": "https://sh.lianjia.com/zufang/SH2151662028098371584.html",
      "rent_type": "整租",
      "location": "普陀-长寿路-上海知音苑",
      "scraped_at": "2026-04-23 15:24:53",
      "region": "changshoulu",
      "unit_price": 106.3,
      "lat": null,
      "lng": null
    },
    {
      "title": "整租·源达大厦 1室1厅 东",
      "community": "源达大厦",
      "area": "49.59",
      "rooms": "1室1厅",
      "direction": "东",
      "floor": "",
      "price": "7500",
      "tags": "",
      "source": "",
      "url": "https://sh.lianjia.com/zufang/SH2091537046794403840.html",
      "rent_type": "整租",
      "location": "普陀-长寿路-源达大厦",
      "scraped_at": "2026-04-23 15:24:53",
      "region": "changshoulu",
      "unit_price": 151.2,
      "lat": null,
      "lng": null
    },
    {
      "title": "整租·世纪之门 2室1厅 东/东南",
      "community": "世纪之门",
      "area": "60.00",
      "rooms": "2室1厅",
      "direction": "东/东南",
      "floor": "",
      "price": "6500",
      "tags": "",
      "source": "",
      "url": "https://sh.lianjia.com/zufang/SH2130679790854733824.html",
      "rent_type": "整租",
      "location": "普陀-长寿路-世纪之门",
      "scraped_at": "2026-04-23 15:24:53",
      "region": "changshoulu",
      "unit_price": 108.3,
      "lat": null,
      "lng": null
    },
    {
      "title": "整租·世纪之门 2室1厅 南",
      "community": "世纪之门",
      "area": "60.61",
      "rooms": "2室1厅",
      "direction": "南",
      "floor": "",
      "price": "6200",
      "tags": "",
      "source": "",
      "url": "https://sh.lianjia.com/zufang/SH2156719749541658624.html",
      "rent_type": "整租",
      "location": "普陀-长寿路-世纪之门",
      "scraped_at": "2026-04-23 15:24:53",
      "region": "changshoulu",
      "unit_price": 102.3,
      "lat": null,
      "lng": null
    },
    {
      "title": "整租·澳门大厦 2室1厅 西南",
      "community": "澳门大厦",
      "area": "87.18",
      "rooms": "2室1厅",
      "direction": "西南",
      "floor": "",
      "price": "7500",
      "tags": "",
      "source": "",
      "url": "https://sh.lianjia.com/zufang/SH2148658915842195456.html",
      "rent_type": "整租",
      "location": "普陀-长寿路-澳门大厦",
      "scraped_at": "2026-04-23 15:24:53",
      "region": "changshoulu",
      "unit_price": 86.0,
      "lat": null,
      "lng": null
    },
    {
      "title": "整租·西部俊园 3室2厅 南/北",
      "community": "西部俊园",
      "area": "135.00",
      "rooms": "3室2厅",
      "direction": "南/北",
      "floor": "",
      "price": "12390",
      "tags": "",
      "source": "",
      "url": "https://sh.lianjia.com/zufang/SH1913229532546990080.html",
      "rent_type": "整租",
      "location": "普陀-长寿路-西部俊园",
      "scraped_at": "2026-04-23 15:24:56",
      "region": "changshoulu",
      "unit_price": 91.8,
      "lat": null,
      "lng": null
    },
    {
      "title": "整租·乐活居 1室1厅 东北",
      "community": "乐活居",
      "area": "52.52",
      "rooms": "1室1厅",
      "direction": "东北",
      "floor": "",
      "price": "5800",
      "tags": "",
      "source": "",
      "url": "https://sh.lianjia.com/zufang/SH2564271635481755648.html",
      "rent_type": "整租",
      "location": "普陀-长寿路-乐活居",
      "scraped_at": "2026-04-23 15:24:56",
      "region": "changshoulu",
      "unit_price": 110.4,
      "lat": null,
      "lng": null
    },
    {
      "title": "整租·华生大厦 3室2厅 东/东南/南",
      "community": "华生大厦",
      "area": "135.63",
      "rooms": "3室2厅",
      "direction": "东/东南/南",
      "floor": "",
      "price": "10500",
      "tags": "",
      "source": "",
      "url": "https://sh.lianjia.com/zufang/SH2154454800723345408.html",
      "rent_type": "整租",
      "location": "普陀-长寿路-华生大厦",
      "scraped_at": "2026-04-23 15:24:56",
      "region": "changshoulu",
      "unit_price": 77.4,
      "lat": null,
      "lng": null
    },
    {
      "title": "整租·澳门小区 1室1厅 南",
      "community": "澳门小区",
      "area": "41.83",
      "rooms": "1室1厅",
      "direction": "南",
      "floor": "",
      "price": "4500",
      "tags": "",
      "source": "",
      "url": "https://sh.lianjia.com/zufang/SH2156693862003769344.html",
      "rent_type": "整租",
      "location": "普陀-长寿路-澳门小区",
      "scraped_at": "2026-04-23 15:24:56",
      "region": "changshoulu",
      "unit_price": 107.6,
      "lat": null,
      "lng": null
    },
    {
      "title": "整租·新天大厦 1室1厅 东",
      "community": "新天大厦",
      "area": "48.00",
      "rooms": "1室1厅",
      "direction": "东",
      "floor": "",
      "price": "4500",
      "tags": "",
      "source": "",
      "url": "https://sh.lianjia.com/zufang/SH2151608823448600576.html",
      "rent_type": "整租",
      "location": "普陀-长寿路-新天大厦",
      "scraped_at": "2026-04-23 15:24:56",
      "region": "changshoulu",
      "unit_price": 93.8,
      "lat": null,
      "lng": null
    },
    {
      "title": "整租·世纪之门 1室1厅 东北",
      "community": "世纪之门",
      "area": "29.90",
      "rooms": "1室1厅",
      "direction": "东北",
      "floor": "",
      "price": "4000",
      "tags": "",
      "source": "",
      "url": "https://sh.lianjia.com/zufang/SH2117277450097393664.html",
      "rent_type": "整租",
      "location": "普陀-长寿路-世纪之门",
      "scraped_at": "2026-04-23 15:25:00",
      "region": "changshoulu",
      "unit_price": 133.8,
      "lat": null,
      "lng": null
    },
    {
      "title": "整租·汤臣豪园一期 4室2厅 南",
      "community": "汤臣豪园一期",
      "area": "188.63",
      "rooms": "4室2厅",
      "direction": "南",
      "floor": "",
      "price": "25000",
      "tags": "",
      "source": "",
      "url": "https://sh.lianjia.com/zufang/SH2140457501286465536.html",
      "rent_type": "整租",
      "location": "浦东-张江-汤臣豪园一期",
      "scraped_at": "2026-04-23 15:25:42",
      "region": "changshoulu",
      "unit_price": 132.5,
      "lat": 31.211262,
      "lng": 121.584802
    },
    {
      "title": "整租·汤臣豪园一期 4室2厅 复式 南",
      "community": "汤臣豪园一期",
      "area": "257.23",
      "rooms": "4室2厅",
      "direction": "",
      "floor": "",
      "price": "26000",
      "tags": "",
      "source": "",
      "url": "https://sh.lianjia.com/zufang/SH2154797458205442048.html",
      "rent_type": "整租",
      "location": "浦东-张江-汤臣豪园一期",
      "scraped_at": "2026-04-23 15:25:42",
      "region": "changshoulu",
      "unit_price": 101.1,
      "lat": 31.211262,
      "lng": 121.584802
    },
    {
      "title": "整租·汤臣豪园(二期) 4室2厅 复式 南",
      "community": "汤臣豪园(二期)",
      "area": "226.99",
      "rooms": "4室2厅",
      "direction": "",
      "floor": "",
      "price": "22000",
      "tags": "",
      "source": "",
      "url": "https://sh.lianjia.com/zufang/SH2096606769806573568.html",
      "rent_type": "整租",
      "location": "浦东-张江-汤臣豪园(二期)",
      "scraped_at": "2026-04-23 15:25:42",
      "region": "changshoulu",
      "unit_price": 96.9,
      "lat": 31.202786,
      "lng": 121.596039
    },
    {
      "title": "整租·东郊紫园 5室3厅 复式 南",
      "community": "东郊紫园",
      "area": "456.00",
      "rooms": "5室3厅",
      "direction": "",
      "floor": "",
      "price": "58800",
      "tags": "",
      "source": "",
      "url": "https://sh.lianjia.com/zufang/SH1991443717344460800.html",
      "rent_type": "整租",
      "location": "浦东-张江-东郊紫园",
      "scraped_at": "2026-04-23 15:25:42",
      "region": "changshoulu",
      "unit_price": 128.9,
      "lat": 31.178775,
      "lng": 121.624074
    },
    {
      "title": "整租·东郊紫园 4室2厅 复式 南",
      "community": "东郊紫园",
      "area": "377.41",
      "rooms": "4室2厅",
      "direction": "",
      "floor": "",
      "price": "50000",
      "tags": "",
      "source": "",
      "url": "https://sh.lianjia.com/zufang/SH2075535813352882176.html",
      "rent_type": "整租",
      "location": "浦东-张江-东郊紫园",
      "scraped_at": "2026-04-23 15:25:42",
      "region": "changshoulu",
      "unit_price": 132.5,
      "lat": 31.178775,
      "lng": 121.624074
    },
    {
      "title": "整租·万科翡翠公园三期 4室2厅 南",
      "community": "万科翡翠公园三期",
      "area": "211.30",
      "rooms": "4室2厅",
      "direction": "南",
      "floor": "",
      "price": "20000",
      "tags": "",
      "source": "",
      "url": "https://sh.lianjia.com/zufang/SH2146820704148914176.html",
      "rent_type": "整租",
      "location": "浦东-张江-万科翡翠公园三期",
      "scraped_at": "2026-04-23 15:25:42",
      "region": "changshoulu",
      "unit_price": 94.7,
      "lat": 31.180094,
      "lng": 121.610047
    },
    {
      "title": "整租·东郊紫园 5室2厅 复式 南",
      "community": "东郊紫园",
      "area": "377.00",
      "rooms": "5室2厅",
      "direction": "",
      "floor": "",
      "price": "40000",
      "tags": "",
      "source": "",
      "url": "https://sh.lianjia.com/zufang/SH2153059674553843712.html",
      "rent_type": "整租",
      "location": "浦东-张江-东郊紫园",
      "scraped_at": "2026-04-23 15:25:42",
      "region": "changshoulu",
      "unit_price": 106.1,
      "lat": 31.178775,
      "lng": 121.624074
    },
    {
      "title": "整租·万科翡翠公园四期 4室2厅 南/北",
      "community": "万科翡翠公园四期",
      "area": "179.82",
      "rooms": "4室2厅",
      "direction": "南/北",
      "floor": "",
      "price": "25000",
      "tags": "",
      "source": "",
      "url": "https://sh.lianjia.com/zufang/SH2150263552722599936.html",
      "rent_type": "整租",
      "location": "浦东-张江-万科翡翠公园四期",
      "scraped_at": "2026-04-23 15:25:00",
      "region": "changshoulu",
      "unit_price": 139.0,
      "lat": 31.179139,
      "lng": 121.610609
    },
    {
      "title": "整租·万科翡翠公园五期 3室3厅 东南",
      "community": "万科翡翠公园五期",
      "area": "148.89",
      "rooms": "3室3厅",
      "direction": "东南",
      "floor": "",
      "price": "21000",
      "tags": "",
      "source": "",
      "url": "https://sh.lianjia.com/zufang/SH2155588429230899200.html",
      "rent_type": "整租",
      "location": "浦东-张江-万科翡翠公园五期",
      "scraped_at": "2026-04-23 15:25:42",
      "region": "changshoulu",
      "unit_price": 141.0,
      "lat": 31.180249,
      "lng": 121.61266
    }
  ],
  "completed": true
}